[
  {
    "author": "YULION",
    "link_thumb": "https://live.staticflickr.com/65535/51672183970_c5651ce16f_o.gif",
    "link_bin": "https://github.com/lmbstudiocontact/mb4_0/raw/main/11644.bin",
    "id_bin": "11644",
    "list_language": [],
    "array_tags": [
      "digital",
      "date",
      "analog",
      "seconds",
      "floors",
      "distance",
      "heartrate",
      "weather",
      "calories",
      "battery",
      "steps"
    ],
    "list_album": [
      {
        "id_album": "518493954",
        "link_thumb": "https://live.staticflickr.com/65535/51672183970_c5651ce16f_o.gif",
        "title": "Other 2"
      }
    ]
  },
  {
    "author": "YULION",
    "link_thumb": "https://live.staticflickr.com/65535/51671992704_fa1f2fc74d_o.gif",
    "link_bin": "https://github.com/lmbstudiocontact/mb4_0/raw/main/11645.bin",
    "id_bin": "11645",
    "list_language": [],
    "array_tags": [
      "digital",
      "date",
      "analog",
      "seconds",
      "floors",
      "distance",
      "heartrate",
      "weather",
      "calories",
      "battery",
      "steps"
    ],
    "list_album": [
      {
        "id_album": "518493954",
        "link_thumb": "https://live.staticflickr.com/65535/51671992704_fa1f2fc74d_o.gif",
        "title": "Other 2"
      }
    ]
  },
  {
    "author": "yajc131988",
    "link_thumb": "https://live.staticflickr.com/65535/51672184985_1dfa100485_o.gif",
    "link_bin": "https://github.com/lmbstudiocontact/mb4_0/raw/main/11657.bin",
    "id_bin": "11657",
    "list_language": [],
    "array_tags": [
      "digital",
      "date",
      "distance",
      "steps"
    ],
    "list_album": [
      {
        "id_album": "518493954",
        "link_thumb": "https://live.staticflickr.com/65535/51672184985_1dfa100485_o.gif",
        "title": "Other 2"
      }
    ]
  },
  {
    "author": "mad max",
    "link_thumb": "https://live.staticflickr.com/65535/51671554393_d62d6180a9_o.gif",
    "link_bin": "https://github.com/lmbstudiocontact/mb4_0/raw/main/11685.bin",
    "id_bin": "11685",
    "list_language": [],
    "array_tags": [
      "digital",
      "date",
      "seconds",
      "heartrate",
      "battery",
      "steps"
    ],
    "list_album": [
      {
        "id_album": "518493954",
        "link_thumb": "https://live.staticflickr.com/65535/51671554393_d62d6180a9_o.gif",
        "title": "Other 2"
      }
    ]
  },
  {
    "author": "lucasboyzao",
    "link_thumb": "https://live.staticflickr.com/65535/51671556603_2316a3e4ed_o.gif",
    "link_bin": "https://github.com/lmbstudiocontact/mb4_0/raw/main/11697.bin",
    "id_bin": "11697",
    "list_language": [],
    "array_tags": [
      "brasil",
      "futebol"
    ],
    "list_album": [
      {
        "id_album": "518493954",
        "link_thumb": "https://live.staticflickr.com/65535/51671556603_2316a3e4ed_o.gif",
        "title": "Other 2"
      }
    ]
  },
  {
    "author": "sunnyt571",
    "link_thumb": "https://live.staticflickr.com/65535/51671317131_ef0a8bcbfa_o.gif",
    "link_bin": "https://github.com/lmbstudiocontact/mb4_0/raw/main/11714.bin",
    "id_bin": "11714",
    "list_language": [],
    "array_tags": [
      "digital",
      "date",
      "battery",
      "steps"
    ],
    "list_album": [
      {
        "id_album": "518493954",
        "link_thumb": "https://live.staticflickr.com/65535/51671317131_ef0a8bcbfa_o.gif",
        "title": "Other 2"
      }
    ]
  },
  {
    "author": "betopiassa",
    "link_thumb": "https://live.staticflickr.com/65535/51671729273_0e8d85959c_o.gif",
    "link_bin": "https://github.com/lmbstudiocontact/mb4_1/raw/main/1598.bin",
    "id_bin": "1598",
    "list_language": [],
    "array_tags": [
      "retro"
    ],
    "list_album": [
      {
        "id_album": "518493954",
        "link_thumb": "https://live.staticflickr.com/65535/51671729273_0e8d85959c_o.gif",
        "title": "Other 2"
      }
    ]
  },
  {
    "author": "betopiassa",
    "link_thumb": "https://live.staticflickr.com/65535/51671490206_7ec17a9a28_o.gif",
    "link_bin": "https://github.com/lmbstudiocontact/mb4_1/raw/main/1599.bin",
    "id_bin": "1599",
    "list_language": [],
    "array_tags": [
      "athletico"
    ],
    "list_album": [
      {
        "id_album": "518493954",
        "link_thumb": "https://live.staticflickr.com/65535/51671490206_7ec17a9a28_o.gif",
        "title": "Other 2"
      }
    ]
  },
  {
    "author": "Shayanrj",
    "link_thumb": "https://live.staticflickr.com/65535/51671742833_35eb79b0c9_o.gif",
    "link_bin": "https://github.com/lmbstudiocontact/mb4_1/raw/main/1709.bin",
    "id_bin": "1709",
    "list_language": [],
    "array_tags": [
      "digital",
      "date",
      "battery",
      "steps"
    ],
    "list_album": [
      {
        "id_album": "518493954",
        "link_thumb": "https://live.staticflickr.com/65535/51671742833_35eb79b0c9_o.gif",
        "title": "Other 2"
      }
    ]
  },
  {
    "author": "CarlosT86",
    "link_thumb": "https://live.staticflickr.com/65535/51671802308_fd5d60cb05_o.gif",
    "link_bin": "https://github.com/lmbstudiocontact/mb4_1/raw/main/1765.bin",
    "id_bin": "1765",
    "list_language": [],
    "array_tags": [
      "music",
      "colors"
    ],
    "list_album": [
      {
        "id_album": "518493954",
        "link_thumb": "https://live.staticflickr.com/65535/51671802308_fd5d60cb05_o.gif",
        "title": "Other 2"
      }
    ]
  },
  {
    "author": "CarlosT86",
    "link_thumb": "https://live.staticflickr.com/65535/51671564391_b219b349c4_o.gif",
    "link_bin": "https://github.com/lmbstudiocontact/mb4_1/raw/main/1767.bin",
    "id_bin": "1767",
    "list_language": [],
    "array_tags": [
      "love",
      "white"
    ],
    "list_album": [
      {
        "id_album": "518493954",
        "link_thumb": "https://live.staticflickr.com/65535/51671564391_b219b349c4_o.gif",
        "title": "Other 2"
      }
    ]
  },
  {
    "author": "CarlosT86",
    "link_thumb": "https://live.staticflickr.com/65535/51672244654_92eff8f8b5_o.gif",
    "link_bin": "https://github.com/lmbstudiocontact/mb4_1/raw/main/1768.bin",
    "id_bin": "1768",
    "list_language": [],
    "array_tags": [
      "love",
      "rock",
      "music",
      "white"
    ],
    "list_album": [
      {
        "id_album": "518493954",
        "link_thumb": "https://live.staticflickr.com/65535/51672244654_92eff8f8b5_o.gif",
        "title": "Other 2"
      }
    ]
  },
  {
    "author": "CarlosT86",
    "link_thumb": "https://live.staticflickr.com/65535/51671566111_5510b0f060_o.gif",
    "link_bin": "https://github.com/lmbstudiocontact/mb4_1/raw/main/1769.bin",
    "id_bin": "1769",
    "list_language": [],
    "array_tags": [
      "rock",
      "music",
      "white"
    ],
    "list_album": [
      {
        "id_album": "518493954",
        "link_thumb": "https://live.staticflickr.com/65535/51671566111_5510b0f060_o.gif",
        "title": "Other 2"
      }
    ]
  },
  {
    "author": "CarlosT86",
    "link_thumb": "https://live.staticflickr.com/65535/51671596326_8689dc2133_o.gif",
    "link_bin": "https://github.com/lmbstudiocontact/mb4_1/raw/main/1795.bin",
    "id_bin": "1795",
    "list_language": [],
    "array_tags": [
      "love",
      "colors",
      "heart"
    ],
    "list_album": [
      {
        "id_album": "518493954",
        "link_thumb": "https://live.staticflickr.com/65535/51671596326_8689dc2133_o.gif",
        "title": "Other 2"
      }
    ]
  },
  {
    "author": "CarlosT86",
    "link_thumb": "https://live.staticflickr.com/65535/51671840948_524b389c66_o.gif",
    "link_bin": "https://github.com/lmbstudiocontact/mb4_1/raw/main/1798.bin",
    "id_bin": "1798",
    "list_language": [],
    "array_tags": [
      "rock",
      "music",
      "white"
    ],
    "list_album": [
      {
        "id_album": "518493954",
        "link_thumb": "https://live.staticflickr.com/65535/51671840948_524b389c66_o.gif",
        "title": "Other 2"
      }
    ]
  },
  {
    "author": "kratellismorru",
    "link_thumb": "https://live.staticflickr.com/65535/51672327198_8996de03c2_o.gif",
    "link_bin": "https://github.com/lmbstudiocontact/mb4_10/raw/main/5668.bin",
    "id_bin": "5668",
    "list_language": [],
    "array_tags": [
      "digital",
      "date",
      "steps"
    ],
    "list_album": [
      {
        "id_album": "518493954",
        "link_thumb": "https://live.staticflickr.com/65535/51672327198_8996de03c2_o.gif",
        "title": "Other 2"
      }
    ]
  },
  {
    "author": "beltra02",
    "link_thumb": "https://live.staticflickr.com/65535/51672958385_88744f8848_o.gif",
    "link_bin": "https://github.com/lmbstudiocontact/mb4_10/raw/main/568.bin",
    "id_bin": "568",
    "list_language": [],
    "array_tags": [
      "digital",
      "date",
      "battery",
      "steps"
    ],
    "list_album": [
      {
        "id_album": "518493954",
        "link_thumb": "https://live.staticflickr.com/65535/51672958385_88744f8848_o.gif",
        "title": "Other 2"
      }
    ]
  },
  {
    "author": "Igorsantana1507",
    "link_thumb": "https://live.staticflickr.com/65535/51672355298_e2c98a35f8_o.gif",
    "link_bin": "https://github.com/lmbstudiocontact/mb4_10/raw/main/5844.bin",
    "id_bin": "5844",
    "list_language": [],
    "array_tags": [
      "date",
      "digital",
      "battery",
      "steps"
    ],
    "list_album": [
      {
        "id_album": "518493954",
        "link_thumb": "https://live.staticflickr.com/65535/51672355298_e2c98a35f8_o.gif",
        "title": "Other 2"
      }
    ]
  },
  {
    "author": "Oswaldo Rey",
    "link_thumb": "https://live.staticflickr.com/65535/51672802304_d88a3dc43a_o.gif",
    "link_bin": "https://github.com/lmbstudiocontact/mb4_10/raw/main/5901.bin",
    "id_bin": "5901",
    "list_language": [],
    "array_tags": [
      "digital",
      "date",
      "battery",
      "steps"
    ],
    "list_album": [
      {
        "id_album": "518493954",
        "link_thumb": "https://live.staticflickr.com/65535/51672802304_d88a3dc43a_o.gif",
        "title": "Other 2"
      }
    ]
  },
  {
    "author": "CipS",
    "link_thumb": "https://live.staticflickr.com/65535/51671326837_4a95147688_o.gif",
    "link_bin": "https://github.com/lmbstudiocontact/mb4_10/raw/main/594.bin",
    "id_bin": "594",
    "list_language": [],
    "array_tags": [
      "digital",
      "battery"
    ],
    "list_album": [
      {
        "id_album": "518493954",
        "link_thumb": "https://live.staticflickr.com/65535/51671326837_4a95147688_o.gif",
        "title": "Other 2"
      }
    ]
  },
  {
    "author": "kratellismorru",
    "link_thumb": "https://live.staticflickr.com/65535/51672998200_a6133bc4f4_o.gif",
    "link_bin": "https://github.com/lmbstudiocontact/mb4_10/raw/main/5945.bin",
    "id_bin": "5945",
    "list_language": [],
    "array_tags": [
      "digital",
      "date",
      "battery",
      "steps"
    ],
    "list_album": [
      {
        "id_album": "518493954",
        "link_thumb": "https://live.staticflickr.com/65535/51672998200_a6133bc4f4_o.gif",
        "title": "Other 2"
      }
    ]
  },
  {
    "author": "ragada",
    "link_thumb": "https://live.staticflickr.com/65535/51670922592_a15283d0a2_o.gif",
    "link_bin": "https://github.com/lmbstudiocontact/mb4_6/raw/main/2473.bin",
    "id_bin": "2473",
    "list_language": [],
    "array_tags": [
      "digital",
      "date",
      "battery",
      "steps"
    ],
    "list_album": [
      {
        "id_album": "518493954",
        "link_thumb": "https://live.staticflickr.com/65535/51670922592_a15283d0a2_o.gif",
        "title": "Other 2"
      }
    ]
  },
  {
    "author": "mequelusso",
    "link_thumb": "https://live.staticflickr.com/65535/51672408029_65d2e31807_o.gif",
    "link_bin": "https://github.com/lmbstudiocontact/mb4_6/raw/main/2538.bin",
    "id_bin": "2538",
    "list_language": [],
    "array_tags": [
      "date",
      "digital"
    ],
    "list_album": [
      {
        "id_album": "518493954",
        "link_thumb": "https://live.staticflickr.com/65535/51672408029_65d2e31807_o.gif",
        "title": "Other 2"
      }
    ]
  },
  {
    "author": "xtovul",
    "link_thumb": "https://live.staticflickr.com/65535/51672413954_7b952b8814_o.gif",
    "link_bin": "https://github.com/lmbstudiocontact/mb4_6/raw/main/2584.bin",
    "id_bin": "2584",
    "list_language": [],
    "array_tags": [
      "digital",
      "date",
      "distance",
      "calories",
      "battery",
      "steps"
    ],
    "list_album": [
      {
        "id_album": "518493954",
        "link_thumb": "https://live.staticflickr.com/65535/51672413954_7b952b8814_o.gif",
        "title": "Other 2"
      }
    ]
  },
  {
    "author": "Fulina6",
    "link_thumb": "https://live.staticflickr.com/65535/51671736481_0f1ef1f999_o.gif",
    "link_bin": "https://github.com/lmbstudiocontact/mb4_6/raw/main/2604.bin",
    "id_bin": "2604",
    "list_language": [],
    "array_tags": [
      "date",
      "battery",
      "steps"
    ],
    "list_album": [
      {
        "id_album": "518493954",
        "link_thumb": "https://live.staticflickr.com/65535/51671736481_0f1ef1f999_o.gif",
        "title": "Other 2"
      }
    ]
  },
  {
    "author": "newesc",
    "link_thumb": "https://live.staticflickr.com/65535/51670937512_1bfd909eed_o.gif",
    "link_bin": "https://github.com/lmbstudiocontact/mb4_6/raw/main/2625.bin",
    "id_bin": "2625",
    "list_language": [],
    "array_tags": [],
    "list_album": [
      {
        "id_album": "518493954",
        "link_thumb": "https://live.staticflickr.com/65535/51670937512_1bfd909eed_o.gif",
        "title": "Other 2"
      }
    ]
  },
  {
    "author": "newesc",
    "link_thumb": "https://live.staticflickr.com/65535/51670938137_9e7e5279dd_o.gif",
    "link_bin": "https://github.com/lmbstudiocontact/mb4_6/raw/main/2627.bin",
    "id_bin": "2627",
    "list_language": [],
    "array_tags": [],
    "list_album": [
      {
        "id_album": "518493954",
        "link_thumb": "https://live.staticflickr.com/65535/51670938137_9e7e5279dd_o.gif",
        "title": "Other 2"
      }
    ]
  },
  {
    "author": "Techdroy",
    "link_thumb": "https://live.staticflickr.com/65535/51671751126_5f667a1151_o.gif",
    "link_bin": "https://github.com/lmbstudiocontact/mb4_6/raw/main/2682.bin",
    "id_bin": "2682",
    "list_language": [],
    "array_tags": [
      "logo"
    ],
    "list_album": [
      {
        "id_album": "518493954",
        "link_thumb": "https://live.staticflickr.com/65535/51671751126_5f667a1151_o.gif",
        "title": "Other 2"
      }
    ]
  },
  {
    "author": "she1kbd_",
    "link_thumb": "https://live.staticflickr.com/65535/51671751431_0fec569032_o.gif",
    "link_bin": "https://github.com/lmbstudiocontact/mb4_6/raw/main/2684.bin",
    "id_bin": "2684",
    "list_language": [],
    "array_tags": [
      "digital",
      "date",
      "portugues",
      "battery",
      "steps"
    ],
    "list_album": [
      {
        "id_album": "518493954",
        "link_thumb": "https://live.staticflickr.com/65535/51671751431_0fec569032_o.gif",
        "title": "Other 2"
      }
    ]
  },
  {
    "author": "Luca_it",
    "link_thumb": "https://live.staticflickr.com/65535/51672005438_67930c169d_o.gif",
    "link_bin": "https://github.com/lmbstudiocontact/mb4_6/raw/main/274.bin",
    "id_bin": "274",
    "list_language": [],
    "array_tags": [
      "digital",
      "date",
      "blue",
      "white",
      "steps"
    ],
    "list_album": [
      {
        "id_album": "518493954",
        "link_thumb": "https://live.staticflickr.com/65535/51672005438_67930c169d_o.gif",
        "title": "Other 2"
      }
    ]
  },
  {
    "author": "ANTIKOR82",
    "link_thumb": "https://live.staticflickr.com/65535/51672473329_0be68c6ca1_o.gif",
    "link_bin": "https://github.com/lmbstudiocontact/mb4_6/raw/main/2907.bin",
    "id_bin": "2907",
    "list_language": [],
    "array_tags": [
      "stalker"
    ],
    "list_album": [
      {
        "id_album": "518493954",
        "link_thumb": "https://live.staticflickr.com/65535/51672473329_0be68c6ca1_o.gif",
        "title": "Other 2"
      }
    ]
  },
  {
    "author": "recepeses26",
    "link_thumb": "https://live.staticflickr.com/65535/51670999837_a5bb60bfd0_o.gif",
    "link_bin": "https://github.com/lmbstudiocontact/mb4_6/raw/main/2969.bin",
    "id_bin": "2969",
    "list_language": [],
    "array_tags": [
      "digital",
      "date",
      "battery"
    ],
    "list_album": [
      {
        "id_album": "518493954",
        "link_thumb": "https://live.staticflickr.com/65535/51670999837_a5bb60bfd0_o.gif",
        "title": "Other 2"
      }
    ]
  },
  {
    "author": "recepeses26",
    "link_thumb": "https://live.staticflickr.com/65535/51672671955_8ca9600d13_o.gif",
    "link_bin": "https://github.com/lmbstudiocontact/mb4_6/raw/main/2971.bin",
    "id_bin": "2971",
    "list_language": [],
    "array_tags": [
      "digital",
      "date",
      "battery"
    ],
    "list_album": [
      {
        "id_album": "518493954",
        "link_thumb": "https://live.staticflickr.com/65535/51672671955_8ca9600d13_o.gif",
        "title": "Other 2"
      }
    ]
  },
  {
    "author": "ataualpa",
    "link_thumb": "https://live.staticflickr.com/65535/51671003972_73152a05ab_o.gif",
    "link_bin": "https://github.com/lmbstudiocontact/mb4_6/raw/main/3019.bin",
    "id_bin": "3019",
    "list_language": [],
    "array_tags": [],
    "list_album": [
      {
        "id_album": "518493954",
        "link_thumb": "https://live.staticflickr.com/65535/51671003972_73152a05ab_o.gif",
        "title": "Other 2"
      }
    ]
  },
  {
    "author": "quangcuong",
    "link_thumb": "https://live.staticflickr.com/65535/51671805706_000b0a0ee8_o.gif",
    "link_bin": "https://github.com/lmbstudiocontact/mb4_6/raw/main/303.bin",
    "id_bin": "303",
    "list_language": [],
    "array_tags": [
      "digital",
      "date",
      "analog",
      "seconds",
      "battery",
      "steps"
    ],
    "list_album": [
      {
        "id_album": "518493954",
        "link_thumb": "https://live.staticflickr.com/65535/51671805706_000b0a0ee8_o.gif",
        "title": "Other 2"
      }
    ]
  },
  {
    "author": "anasmel",
    "link_thumb": "https://live.staticflickr.com/65535/51671811936_40340089c4_o.gif",
    "link_bin": "https://github.com/lmbstudiocontact/mb4_6/raw/main/3097.bin",
    "id_bin": "3097",
    "list_language": [],
    "array_tags": [
      "paok"
    ],
    "list_album": [
      {
        "id_album": "518493954",
        "link_thumb": "https://live.staticflickr.com/65535/51671811936_40340089c4_o.gif",
        "title": "Other 2"
      }
    ]
  },
  {
    "author": "recepeses26",
    "link_thumb": "https://live.staticflickr.com/65535/51672493674_3efa2a1c37_o.gif",
    "link_bin": "https://github.com/lmbstudiocontact/mb4_6/raw/main/3121.bin",
    "id_bin": "3121",
    "list_language": [],
    "array_tags": [
      "date",
      "seconds",
      "battery"
    ],
    "list_album": [
      {
        "id_album": "518493954",
        "link_thumb": "https://live.staticflickr.com/65535/51672493674_3efa2a1c37_o.gif",
        "title": "Other 2"
      }
    ]
  },
  {
    "author": "orantino",
    "link_thumb": "https://live.staticflickr.com/65535/51672053518_411ccf2ba7_o.gif",
    "link_bin": "https://github.com/lmbstudiocontact/mb4_6/raw/main/3124.bin",
    "id_bin": "3124",
    "list_language": [],
    "array_tags": [
      "digital",
      "date",
      "distance",
      "heartrate",
      "calories",
      "battery",
      "steps"
    ],
    "list_album": [
      {
        "id_album": "518493954",
        "link_thumb": "https://live.staticflickr.com/65535/51672053518_411ccf2ba7_o.gif",
        "title": "Other 2"
      }
    ]
  },
  {
    "author": "troull88",
    "link_thumb": "https://live.staticflickr.com/65535/51672689560_c7866a43c6_o.gif",
    "link_bin": "https://github.com/lmbstudiocontact/mb4_6/raw/main/3174.bin",
    "id_bin": "3174",
    "list_language": [],
    "array_tags": [
      "digital",
      "date",
      "heartrate",
      "battery",
      "steps"
    ],
    "list_album": [
      {
        "id_album": "518493954",
        "link_thumb": "https://live.staticflickr.com/65535/51672689560_c7866a43c6_o.gif",
        "title": "Other 2"
      }
    ]
  },
  {
    "author": "dw4ever",
    "link_thumb": "https://live.staticflickr.com/65535/51671026422_8a71ee9871_o.gif",
    "link_bin": "https://github.com/lmbstudiocontact/mb4_6/raw/main/3264.bin",
    "id_bin": "3264",
    "list_language": [],
    "array_tags": [
      "date",
      "digital",
      "battery",
      "steps"
    ],
    "list_album": [
      {
        "id_album": "518493954",
        "link_thumb": "https://live.staticflickr.com/65535/51671026422_8a71ee9871_o.gif",
        "title": "Other 2"
      }
    ]
  },
  {
    "author": "metfan",
    "link_thumb": "https://live.staticflickr.com/65535/51672508739_ee3bc3fc29_o.gif",
    "link_bin": "https://github.com/lmbstudiocontact/mb4_6/raw/main/3286.bin",
    "id_bin": "3286",
    "list_language": [],
    "array_tags": [
      "watch",
      "time",
      "steps"
    ],
    "list_album": [
      {
        "id_album": "518493954",
        "link_thumb": "https://live.staticflickr.com/65535/51672508739_ee3bc3fc29_o.gif",
        "title": "Other 2"
      }
    ]
  },
  {
    "author": "noesabiel",
    "link_thumb": "https://live.staticflickr.com/65535/51672510579_bdc9d8715c_o.gif",
    "link_bin": "https://github.com/lmbstudiocontact/mb4_6/raw/main/3303.bin",
    "id_bin": "3303",
    "list_language": [
      {
        "author": "noesabiel",
        "link_thumb": "https://live.staticflickr.com/65535/51672070528_26722dc8d3_o.gif",
        "link_bin": "https://github.com/lmbstudiocontact/mb4_6/raw/main/3303_English.bin",
        "name_language": "English",
        "id_bin_language": "3303_English"
      },
      {
        "author": "noesabiel",
        "link_thumb": "https://live.staticflickr.com/65535/51672512064_427d89cc5e_o.gif",
        "link_bin": "https://github.com/lmbstudiocontact/mb4_6/raw/main/3303_Portuguese.bin",
        "name_language": "Portuguese",
        "id_bin_language": "3303_Portuguese"
      },
      {
        "author": "noesabiel",
        "link_thumb": "https://live.staticflickr.com/65535/51672071868_b61892a0ec_o.gif",
        "link_bin": "https://github.com/lmbstudiocontact/mb4_6/raw/main/3303_Russian.bin",
        "name_language": "Russian",
        "id_bin_language": "3303_Russian"
      },
      {
        "author": "noesabiel",
        "link_thumb": "https://live.staticflickr.com/65535/51672702745_4909a501eb_o.gif",
        "link_bin": "https://github.com/lmbstudiocontact/mb4_6/raw/main/3303_Spanish.bin",
        "name_language": "Spanish",
        "id_bin_language": "3303_Spanish"
      }
    ],
    "array_tags": [
      "indonesia"
    ],
    "list_album": [
      {
        "id_album": "518493954",
        "link_thumb": "https://live.staticflickr.com/65535/51672510579_bdc9d8715c_o.gif",
        "title": "Other 2"
      }
    ]
  },
  {
    "author": "PoleoDeMenta",
    "link_thumb": "https://live.staticflickr.com/65535/51671034927_a3a12d7e5c_o.gif",
    "link_bin": "https://github.com/lmbstudiocontact/mb4_6/raw/main/3340.bin",
    "id_bin": "3340",
    "list_language": [],
    "array_tags": [
      "digital",
      "zelda",
      "battery",
      "steps"
    ],
    "list_album": [
      {
        "id_album": "518493954",
        "link_thumb": "https://live.staticflickr.com/65535/51671034927_a3a12d7e5c_o.gif",
        "title": "Other 2"
      }
    ]
  },
  {
    "author": "Mhcrazy",
    "link_thumb": "https://live.staticflickr.com/65535/51672078923_350afc0cf7_o.gif",
    "link_bin": "https://github.com/lmbstudiocontact/mb4_6/raw/main/3392.bin",
    "id_bin": "3392",
    "list_language": [],
    "array_tags": [
      "digital",
      "date",
      "floors",
      "distance",
      "heartrate",
      "calories",
      "battery",
      "steps"
    ],
    "list_album": [
      {
        "id_album": "518493954",
        "link_thumb": "https://live.staticflickr.com/65535/51672078923_350afc0cf7_o.gif",
        "title": "Other 2"
      }
    ]
  },
  {
    "author": "Oswaldo Rey",
    "link_thumb": "https://live.staticflickr.com/65535/51672082478_e984789b45_o.gif",
    "link_bin": "https://github.com/lmbstudiocontact/mb4_6/raw/main/3419.bin",
    "id_bin": "3419",
    "list_language": [],
    "array_tags": [
      "digital",
      "date",
      "heartrate",
      "battery",
      "steps"
    ],
    "list_album": [
      {
        "id_album": "518493954",
        "link_thumb": "https://live.staticflickr.com/65535/51672082478_e984789b45_o.gif",
        "title": "Other 2"
      }
    ]
  },
  {
    "author": "tutubaba",
    "link_thumb": "https://live.staticflickr.com/65535/51672731125_7e93376a0f_o.gif",
    "link_bin": "https://github.com/lmbstudiocontact/mb4_6/raw/main/3571.bin",
    "id_bin": "3571",
    "list_language": [],
    "array_tags": [
      "digital",
      "calories",
      "steps"
    ],
    "list_album": [
      {
        "id_album": "518493954",
        "link_thumb": "https://live.staticflickr.com/65535/51672731125_7e93376a0f_o.gif",
        "title": "Other 2"
      }
    ]
  },
  {
    "author": "Zackezam",
    "link_thumb": "https://live.staticflickr.com/65535/51672544344_41c23c8419_o.gif",
    "link_bin": "https://github.com/lmbstudiocontact/mb4_6/raw/main/3610.bin",
    "id_bin": "3610",
    "list_language": [],
    "array_tags": [
      "digital",
      "date",
      "distance",
      "heartrate",
      "battery",
      "steps"
    ],
    "list_album": [
      {
        "id_album": "518493954",
        "link_thumb": "https://live.staticflickr.com/65535/51672544344_41c23c8419_o.gif",
        "title": "Other 2"
      }
    ]
  },
  {
    "author": "Jezybuana",
    "link_thumb": "https://live.staticflickr.com/65535/51672546244_ba516d3e7c_o.gif",
    "link_bin": "https://github.com/lmbstudiocontact/mb4_6/raw/main/3654.bin",
    "id_bin": "3654",
    "list_language": [],
    "array_tags": [
      "date",
      "digital",
      "calories",
      "steps"
    ],
    "list_album": [
      {
        "id_album": "518493954",
        "link_thumb": "https://live.staticflickr.com/65535/51672546244_ba516d3e7c_o.gif",
        "title": "Other 2"
      }
    ]
  },
  {
    "author": "Diegox41",
    "link_thumb": "https://live.staticflickr.com/65535/51672567634_30781508ee_o.gif",
    "link_bin": "https://github.com/lmbstudiocontact/mb4_6/raw/main/3900.bin",
    "id_bin": "3900",
    "list_language": [],
    "array_tags": [
      "distance",
      "heartrate",
      "calories",
      "battery",
      "steps"
    ],
    "list_album": [
      {
        "id_album": "518493954",
        "link_thumb": "https://live.staticflickr.com/65535/51672567634_30781508ee_o.gif",
        "title": "Other 2"
      }
    ]
  },
  {
    "author": "Aji saw",
    "link_thumb": "https://live.staticflickr.com/65535/51672758480_56d4c55925_o.gif",
    "link_bin": "https://github.com/lmbstudiocontact/mb4_6/raw/main/3907.bin",
    "id_bin": "3907",
    "list_language": [],
    "array_tags": [
      "date",
      "analog"
    ],
    "list_album": [
      {
        "id_album": "518493954",
        "link_thumb": "https://live.staticflickr.com/65535/51672758480_56d4c55925_o.gif",
        "title": "Other 2"
      }
    ]
  }
]