[
  {
    "author": "GabrielWDSA",
    "link_thumb": "https://live.staticflickr.com/65535/51786890646_93bb99b0a7_o.gif",
    "link_bin": "https://github.com/lmbstudiocontact/mb4_16/raw/main/18913.bin",
    "id_bin": "18913",
    "list_language": [],
    "array_tags": [
      "digital",
      "naruto",
      "steps"
    ],
    "list_album": [
      {
        "id_album": "63410260",
        "link_thumb": "https://live.staticflickr.com/65535/51786890646_93bb99b0a7_o.gif",
        "title": "Anime"
      }
    ]
  },
  {
    "author": "Resalec",
    "link_thumb": "https://live.staticflickr.com/65535/51786890591_c3f14d527d_o.gif",
    "link_bin": "https://github.com/lmbstudiocontact/mb4_16/raw/main/18914.bin",
    "id_bin": "18914",
    "list_language": [],
    "array_tags": [
      "digital",
      "date",
      "battery",
      "steps"
    ],
    "list_album": [
      {
        "id_album": "63410260",
        "link_thumb": "https://live.staticflickr.com/65535/51786890591_c3f14d527d_o.gif",
        "title": "Anime"
      }
    ]
  },
  {
    "author": "bigblackfoot",
    "link_thumb": "https://live.staticflickr.com/65535/51787141688_cab6d88701_o.gif",
    "link_bin": "https://github.com/lmbstudiocontact/mb4_16/raw/main/19043.bin",
    "id_bin": "19043",
    "list_language": [],
    "array_tags": [
      "digital",
      "date",
      "bigblackfoot",
      "weekday",
      "purple",
      "battery",
      "anime"
    ],
    "list_album": [
      {
        "id_album": "63410260",
        "link_thumb": "https://live.staticflickr.com/65535/51787141688_cab6d88701_o.gif",
        "title": "Anime"
      }
    ]
  },
  {
    "author": "CarlosT86",
    "link_thumb": "https://live.staticflickr.com/65535/51786094597_51dde8072f_o.gif",
    "link_bin": "https://github.com/lmbstudiocontact/mb4_21/raw/main/1808.bin",
    "id_bin": "1808",
    "list_language": [],
    "array_tags": [
      "white",
      "skull"
    ],
    "list_album": [
      {
        "id_album": "63410260",
        "link_thumb": "https://live.staticflickr.com/65535/51786094597_51dde8072f_o.gif",
        "title": "Anime"
      }
    ]
  },
  {
    "author": "Nico194",
    "link_thumb": "https://live.staticflickr.com/65535/51787165678_1ccff71f47_o.gif",
    "link_bin": "https://github.com/lmbstudiocontact/mb4_21/raw/main/181.bin",
    "id_bin": "181",
    "list_language": [],
    "array_tags": [
      "digital",
      "date",
      "battery",
      "steps"
    ],
    "list_album": [
      {
        "id_album": "63410260",
        "link_thumb": "https://live.staticflickr.com/65535/51787165678_1ccff71f47_o.gif",
        "title": "Anime"
      }
    ]
  },
  {
    "author": "pureexe",
    "link_thumb": "https://live.staticflickr.com/65535/51787164343_169ea867b7_o.gif",
    "link_bin": "https://github.com/lmbstudiocontact/mb4_21/raw/main/1819.bin",
    "id_bin": "1819",
    "list_language": [],
    "array_tags": [
      "digital",
      "anime"
    ],
    "list_album": [
      {
        "id_album": "63410260",
        "link_thumb": "https://live.staticflickr.com/65535/51787164343_169ea867b7_o.gif",
        "title": "Anime"
      }
    ]
  },
  {
    "author": "pureexe",
    "link_thumb": "https://live.staticflickr.com/65535/51786911571_16881c1765_o.gif",
    "link_bin": "https://github.com/lmbstudiocontact/mb4_21/raw/main/1821.bin",
    "id_bin": "1821",
    "list_language": [],
    "array_tags": [
      "digital",
      "anime"
    ],
    "list_album": [
      {
        "id_album": "63410260",
        "link_thumb": "https://live.staticflickr.com/65535/51786911571_16881c1765_o.gif",
        "title": "Anime"
      }
    ]
  },
  {
    "author": "EnriqueHerrera",
    "link_thumb": "https://live.staticflickr.com/65535/51787164088_d83078b289_o.gif",
    "link_bin": "https://github.com/lmbstudiocontact/mb4_21/raw/main/1838.bin",
    "id_bin": "1838",
    "list_language": [],
    "array_tags": [
      "date",
      "seconds",
      "zelda",
      "battery",
      "steps"
    ],
    "list_album": [
      {
        "id_album": "63410260",
        "link_thumb": "https://live.staticflickr.com/65535/51787164088_d83078b289_o.gif",
        "title": "Anime"
      }
    ]
  },
  {
    "author": "CriZerPE",
    "link_thumb": "https://live.staticflickr.com/65535/51787532984_c61daebed8_o.gif",
    "link_bin": "https://github.com/lmbstudiocontact/mb4_21/raw/main/1851.bin",
    "id_bin": "1851",
    "list_language": [],
    "array_tags": [
      "anime"
    ],
    "list_album": [
      {
        "id_album": "63410260",
        "link_thumb": "https://live.staticflickr.com/65535/51787532984_c61daebed8_o.gif",
        "title": "Anime"
      }
    ]
  },
  {
    "author": "CriZerPE",
    "link_thumb": "https://live.staticflickr.com/65535/51787532934_04600d44ec_o.gif",
    "link_bin": "https://github.com/lmbstudiocontact/mb4_21/raw/main/1852.bin",
    "id_bin": "1852",
    "list_language": [],
    "array_tags": [],
    "list_album": [
      {
        "id_album": "63410260",
        "link_thumb": "https://live.staticflickr.com/65535/51787532934_04600d44ec_o.gif",
        "title": "Anime"
      }
    ]
  },
  {
    "author": "Nico194",
    "link_thumb": "https://live.staticflickr.com/65535/51786912986_5cebba9e7e_o.gif",
    "link_bin": "https://github.com/lmbstudiocontact/mb4_21/raw/main/188.bin",
    "id_bin": "188",
    "list_language": [],
    "array_tags": [
      "date",
      "digital",
      "steps"
    ],
    "list_album": [
      {
        "id_album": "63410260",
        "link_thumb": "https://live.staticflickr.com/65535/51786912986_5cebba9e7e_o.gif",
        "title": "Anime"
      }
    ]
  },
  {
    "author": "phband4",
    "link_thumb": "https://live.staticflickr.com/65535/51787165763_90c95d9995_o.gif",
    "link_bin": "https://github.com/lmbstudiocontact/mb4_21/raw/main/19.bin",
    "id_bin": "19",
    "list_language": [],
    "array_tags": [
      "dragonball",
      "ball",
      "dragon"
    ],
    "list_album": [
      {
        "id_album": "63410260",
        "link_thumb": "https://live.staticflickr.com/65535/51787165763_90c95d9995_o.gif",
        "title": "Anime"
      }
    ]
  },
  {
    "author": "zMadRice",
    "link_thumb": "https://live.staticflickr.com/65535/51787532349_4b3ca502c5_o.gif",
    "link_bin": "https://github.com/lmbstudiocontact/mb4_21/raw/main/1914.bin",
    "id_bin": "1914",
    "list_language": [],
    "array_tags": [
      "date",
      "digital",
      "battery",
      "steps"
    ],
    "list_album": [
      {
        "id_album": "63410260",
        "link_thumb": "https://live.staticflickr.com/65535/51787532349_4b3ca502c5_o.gif",
        "title": "Anime"
      }
    ]
  },
  {
    "author": "zMadRice",
    "link_thumb": "https://live.staticflickr.com/65535/51786093247_8017fed7b7_o.gif",
    "link_bin": "https://github.com/lmbstudiocontact/mb4_21/raw/main/1915.bin",
    "id_bin": "1915",
    "list_language": [],
    "array_tags": [
      "date",
      "seconds",
      "heartrate",
      "battery"
    ],
    "list_album": [
      {
        "id_album": "63410260",
        "link_thumb": "https://live.staticflickr.com/65535/51786093247_8017fed7b7_o.gif",
        "title": "Anime"
      }
    ]
  },
  {
    "author": "MikiXD",
    "link_thumb": "https://live.staticflickr.com/65535/51786097432_89f1219ee8_o.gif",
    "link_bin": "https://github.com/lmbstudiocontact/mb4_21/raw/main/1950.bin",
    "id_bin": "1950",
    "list_language": [],
    "array_tags": [
      "analog"
    ],
    "list_album": [
      {
        "id_album": "63410260",
        "link_thumb": "https://live.staticflickr.com/65535/51786097432_89f1219ee8_o.gif",
        "title": "Anime"
      }
    ]
  },
  {
    "author": "CriZerPE",
    "link_thumb": "https://live.staticflickr.com/65535/51786097387_8334236597_o.gif",
    "link_bin": "https://github.com/lmbstudiocontact/mb4_21/raw/main/1955.bin",
    "id_bin": "1955",
    "list_language": [],
    "array_tags": [
      "gaming"
    ],
    "list_album": [
      {
        "id_album": "63410260",
        "link_thumb": "https://live.staticflickr.com/65535/51786097387_8334236597_o.gif",
        "title": "Anime"
      }
    ]
  },
  {
    "author": "zMadRice",
    "link_thumb": "https://live.staticflickr.com/65535/51787536569_f60bc84ca2_o.gif",
    "link_bin": "https://github.com/lmbstudiocontact/mb4_21/raw/main/1965.bin",
    "id_bin": "1965",
    "list_language": [],
    "array_tags": [
      "date",
      "digital",
      "weather",
      "battery",
      "steps"
    ],
    "list_album": [
      {
        "id_album": "63410260",
        "link_thumb": "https://live.staticflickr.com/65535/51787536569_f60bc84ca2_o.gif",
        "title": "Anime"
      }
    ]
  },
  {
    "author": "MikiXD",
    "link_thumb": "https://live.staticflickr.com/65535/51786914391_953cc746cd_o.gif",
    "link_bin": "https://github.com/lmbstudiocontact/mb4_21/raw/main/1993.bin",
    "id_bin": "1993",
    "list_language": [],
    "array_tags": [
      "battery"
    ],
    "list_album": [
      {
        "id_album": "63410260",
        "link_thumb": "https://live.staticflickr.com/65535/51786914391_953cc746cd_o.gif",
        "title": "Anime"
      }
    ]
  },
  {
    "author": "MikiXD",
    "link_thumb": "https://live.staticflickr.com/65535/51787787300_e31f31c4a3_o.gif",
    "link_bin": "https://github.com/lmbstudiocontact/mb4_21/raw/main/1994.bin",
    "id_bin": "1994",
    "list_language": [],
    "array_tags": [
      "date",
      "steps"
    ],
    "list_album": [
      {
        "id_album": "63410260",
        "link_thumb": "https://live.staticflickr.com/65535/51787787300_e31f31c4a3_o.gif",
        "title": "Anime"
      }
    ]
  },
  {
    "author": "MikiXD",
    "link_thumb": "https://live.staticflickr.com/65535/51787166968_5f9b9e431e_o.gif",
    "link_bin": "https://github.com/lmbstudiocontact/mb4_21/raw/main/1995.bin",
    "id_bin": "1995",
    "list_language": [],
    "array_tags": [
      "digital",
      "battery"
    ],
    "list_album": [
      {
        "id_album": "63410260",
        "link_thumb": "https://live.staticflickr.com/65535/51787166968_5f9b9e431e_o.gif",
        "title": "Anime"
      }
    ]
  },
  {
    "author": "MikiXD",
    "link_thumb": "https://live.staticflickr.com/65535/51787536249_69921bbb64_o.gif",
    "link_bin": "https://github.com/lmbstudiocontact/mb4_21/raw/main/1996.bin",
    "id_bin": "1996",
    "list_language": [],
    "array_tags": [
      "digital"
    ],
    "list_album": [
      {
        "id_album": "63410260",
        "link_thumb": "https://live.staticflickr.com/65535/51787536249_69921bbb64_o.gif",
        "title": "Anime"
      }
    ]
  },
  {
    "author": "MikiXD",
    "link_thumb": "https://live.staticflickr.com/65535/51787166893_1f37a82e7e_o.gif",
    "link_bin": "https://github.com/lmbstudiocontact/mb4_21/raw/main/2000.bin",
    "id_bin": "2000",
    "list_language": [],
    "array_tags": [
      "digital",
      "battery"
    ],
    "list_album": [
      {
        "id_album": "63410260",
        "link_thumb": "https://live.staticflickr.com/65535/51787166893_1f37a82e7e_o.gif",
        "title": "Anime"
      }
    ]
  },
  {
    "author": "minhdale",
    "link_thumb": "https://live.staticflickr.com/65535/51786913611_da7f71b386_o.gif",
    "link_bin": "https://github.com/lmbstudiocontact/mb4_21/raw/main/2045.bin",
    "id_bin": "2045",
    "list_language": [],
    "array_tags": [
      "pokemon"
    ],
    "list_album": [
      {
        "id_album": "63410260",
        "link_thumb": "https://live.staticflickr.com/65535/51786913611_da7f71b386_o.gif",
        "title": "Anime"
      }
    ]
  },
  {
    "author": "minhdale",
    "link_thumb": "https://live.staticflickr.com/65535/51787786610_11ef88cc28_o.gif",
    "link_bin": "https://github.com/lmbstudiocontact/mb4_21/raw/main/2046.bin",
    "id_bin": "2046",
    "list_language": [],
    "array_tags": [
      "pokemon",
      "pikachu"
    ],
    "list_album": [
      {
        "id_album": "63410260",
        "link_thumb": "https://live.staticflickr.com/65535/51787786610_11ef88cc28_o.gif",
        "title": "Anime"
      }
    ]
  },
  {
    "author": "minhdale",
    "link_thumb": "https://live.staticflickr.com/65535/51787166223_25a8e5a703_o.gif",
    "link_bin": "https://github.com/lmbstudiocontact/mb4_21/raw/main/2047.bin",
    "id_bin": "2047",
    "list_language": [],
    "array_tags": [
      "pokemon",
      "pikachu"
    ],
    "list_album": [
      {
        "id_album": "63410260",
        "link_thumb": "https://live.staticflickr.com/65535/51787166223_25a8e5a703_o.gif",
        "title": "Anime"
      }
    ]
  },
  {
    "author": "minhdale",
    "link_thumb": "https://live.staticflickr.com/65535/51787786550_7fbdcf302c_o.gif",
    "link_bin": "https://github.com/lmbstudiocontact/mb4_21/raw/main/2050.bin",
    "id_bin": "2050",
    "list_language": [
      {
        "author": "minhdale",
        "link_thumb": "https://live.staticflickr.com/65535/51787535289_ea672abbb1_o.gif",
        "link_bin": "https://github.com/lmbstudiocontact/mb4_21/raw/main/2050_English.bin",
        "name_language": "English",
        "id_bin_language": "2050_English"
      },
      {
        "author": "minhdale",
        "link_thumb": "https://live.staticflickr.com/65535/51787165948_ef5c69b180_o.gif",
        "link_bin": "https://github.com/lmbstudiocontact/mb4_21/raw/main/2050_Portuguese.bin",
        "name_language": "Portuguese",
        "id_bin_language": "2050_Portuguese"
      },
      {
        "author": "minhdale",
        "link_thumb": "https://live.staticflickr.com/65535/51787535104_1de2752c91_o.gif",
        "link_bin": "https://github.com/lmbstudiocontact/mb4_21/raw/main/2050_Russian.bin",
        "name_language": "Russian",
        "id_bin_language": "2050_Russian"
      },
      {
        "author": "minhdale",
        "link_thumb": "https://live.staticflickr.com/65535/51786095937_8a1c3bf377_o.gif",
        "link_bin": "https://github.com/lmbstudiocontact/mb4_21/raw/main/2050_Spanish.bin",
        "name_language": "Spanish",
        "id_bin_language": "2050_Spanish"
      }
    ],
    "array_tags": [
      "pokemon",
      "pikachu"
    ],
    "list_album": [
      {
        "id_album": "63410260",
        "link_thumb": "https://live.staticflickr.com/65535/51787786550_7fbdcf302c_o.gif",
        "title": "Anime"
      }
    ]
  },
  {
    "author": "minhdale",
    "link_thumb": "https://live.staticflickr.com/65535/51787534959_2cfb8338d4_o.gif",
    "link_bin": "https://github.com/lmbstudiocontact/mb4_21/raw/main/2051.bin",
    "id_bin": "2051",
    "list_language": [],
    "array_tags": [
      "pokemon",
      "pikachu"
    ],
    "list_album": [
      {
        "id_album": "63410260",
        "link_thumb": "https://live.staticflickr.com/65535/51787534959_2cfb8338d4_o.gif",
        "title": "Anime"
      }
    ]
  },
  {
    "author": "AdrianML120",
    "link_thumb": "https://live.staticflickr.com/65535/51786913046_fc2d8a8bd5_o.gif",
    "link_bin": "https://github.com/lmbstudiocontact/mb4_21/raw/main/2052.bin",
    "id_bin": "2052",
    "list_language": [],
    "array_tags": [
      "naruto",
      "red",
      "dark",
      "black",
      "anime"
    ],
    "list_album": [
      {
        "id_album": "63410260",
        "link_thumb": "https://live.staticflickr.com/65535/51786913046_fc2d8a8bd5_o.gif",
        "title": "Anime"
      }
    ]
  },
  {
    "author": "Blacklols",
    "link_thumb": "https://live.staticflickr.com/65535/51786912841_bd1905e502_o.gif",
    "link_bin": "https://github.com/lmbstudiocontact/mb4_21/raw/main/2063.bin",
    "id_bin": "2063",
    "list_language": [],
    "array_tags": [
      "date",
      "battery",
      "steps"
    ],
    "list_album": [
      {
        "id_album": "63410260",
        "link_thumb": "https://live.staticflickr.com/65535/51786912841_bd1905e502_o.gif",
        "title": "Anime"
      }
    ]
  },
  {
    "author": "Xoobit",
    "link_thumb": "https://live.staticflickr.com/65535/51787166218_0a4e739cd7_o.gif",
    "link_bin": "https://github.com/lmbstudiocontact/mb4_21/raw/main/2124.bin",
    "id_bin": "2124",
    "list_language": [],
    "array_tags": [
      "digital",
      "date",
      "battery",
      "steps"
    ],
    "list_album": [
      {
        "id_album": "63410260",
        "link_thumb": "https://live.staticflickr.com/65535/51787166218_0a4e739cd7_o.gif",
        "title": "Anime"
      }
    ]
  },
  {
    "author": "minhdale",
    "link_thumb": "https://live.staticflickr.com/65535/51786096187_c5a624fda3_o.gif",
    "link_bin": "https://github.com/lmbstudiocontact/mb4_21/raw/main/2128.bin",
    "id_bin": "2128",
    "list_language": [],
    "array_tags": [
      "pokemon",
      "pikachu"
    ],
    "list_album": [
      {
        "id_album": "63410260",
        "link_thumb": "https://live.staticflickr.com/65535/51786096187_c5a624fda3_o.gif",
        "title": "Anime"
      }
    ]
  },
  {
    "author": "zMadRice",
    "link_thumb": "https://live.staticflickr.com/65535/51786912951_551c0a5802_o.gif",
    "link_bin": "https://github.com/lmbstudiocontact/mb4_21/raw/main/2149.bin",
    "id_bin": "2149",
    "list_language": [],
    "array_tags": [
      "date",
      "digital",
      "battery",
      "steps"
    ],
    "list_album": [
      {
        "id_album": "63410260",
        "link_thumb": "https://live.staticflickr.com/65535/51786912951_551c0a5802_o.gif",
        "title": "Anime"
      }
    ]
  },
  {
    "author": "zMadRice",
    "link_thumb": "https://live.staticflickr.com/65535/51787786030_0a2eb8f073_o.gif",
    "link_bin": "https://github.com/lmbstudiocontact/mb4_21/raw/main/2150.bin",
    "id_bin": "2150",
    "list_language": [],
    "array_tags": [
      "date",
      "digital",
      "battery",
      "steps"
    ],
    "list_album": [
      {
        "id_album": "63410260",
        "link_thumb": "https://live.staticflickr.com/65535/51787786030_0a2eb8f073_o.gif",
        "title": "Anime"
      }
    ]
  },
  {
    "author": "BySciaa",
    "link_thumb": "https://live.staticflickr.com/65535/51787785440_36e7b908ec_o.gif",
    "link_bin": "https://github.com/lmbstudiocontact/mb4_21/raw/main/2177.bin",
    "id_bin": "2177",
    "list_language": [],
    "array_tags": [
      "miband4",
      "pikachu"
    ],
    "list_album": [
      {
        "id_album": "63410260",
        "link_thumb": "https://live.staticflickr.com/65535/51787785440_36e7b908ec_o.gif",
        "title": "Anime"
      }
    ]
  },
  {
    "author": "huykenichi",
    "link_thumb": "https://live.staticflickr.com/65535/51787789465_0f8aaa7528_o.gif",
    "link_bin": "https://github.com/lmbstudiocontact/mb4_21/raw/main/22.bin",
    "id_bin": "22",
    "list_language": [],
    "array_tags": [
      "chill"
    ],
    "list_album": [
      {
        "id_album": "63410260",
        "link_thumb": "https://live.staticflickr.com/65535/51787789465_0f8aaa7528_o.gif",
        "title": "Anime"
      }
    ]
  },
  {
    "author": "kakheng1996",
    "link_thumb": "https://live.staticflickr.com/65535/51786911731_e119e5973b_o.gif",
    "link_bin": "https://github.com/lmbstudiocontact/mb4_21/raw/main/2207.bin",
    "id_bin": "2207",
    "list_language": [],
    "array_tags": [
      "date",
      "digital",
      "battery",
      "steps"
    ],
    "list_album": [
      {
        "id_album": "63410260",
        "link_thumb": "https://live.staticflickr.com/65535/51786911731_e119e5973b_o.gif",
        "title": "Anime"
      }
    ]
  },
  {
    "author": "TaeVitamin10",
    "link_thumb": "https://live.staticflickr.com/65535/51786093227_71f2cc15b4_o.gif",
    "link_bin": "https://github.com/lmbstudiocontact/mb4_21/raw/main/2249.bin",
    "id_bin": "2249",
    "list_language": [],
    "array_tags": [
      "anime"
    ],
    "list_album": [
      {
        "id_album": "63410260",
        "link_thumb": "https://live.staticflickr.com/65535/51786093227_71f2cc15b4_o.gif",
        "title": "Anime"
      }
    ]
  },
  {
    "author": "kakheng1996",
    "link_thumb": "https://live.staticflickr.com/65535/51787532134_17ae97037a_o.gif",
    "link_bin": "https://github.com/lmbstudiocontact/mb4_21/raw/main/2257.bin",
    "id_bin": "2257",
    "list_language": [],
    "array_tags": [
      "digital",
      "date",
      "battery",
      "steps"
    ],
    "list_album": [
      {
        "id_album": "63410260",
        "link_thumb": "https://live.staticflickr.com/65535/51787532134_17ae97037a_o.gif",
        "title": "Anime"
      }
    ]
  },
  {
    "author": "Edduverdao",
    "link_thumb": "https://live.staticflickr.com/65535/51787783320_aa7d61583c_o.gif",
    "link_bin": "https://github.com/lmbstudiocontact/mb4_21/raw/main/2276.bin",
    "id_bin": "2276",
    "list_language": [],
    "array_tags": [
      "digital",
      "date",
      "analog",
      "seconds",
      "floors",
      "distance",
      "heartrate",
      "weather",
      "calories",
      "battery",
      "steps"
    ],
    "list_album": [
      {
        "id_album": "63410260",
        "link_thumb": "https://live.staticflickr.com/65535/51787783320_aa7d61583c_o.gif",
        "title": "Anime"
      }
    ]
  },
  {
    "author": "VictorFerNBRAZIL",
    "link_thumb": "https://live.staticflickr.com/65535/51787783090_1e3e585453_o.gif",
    "link_bin": "https://github.com/lmbstudiocontact/mb4_21/raw/main/2291.bin",
    "id_bin": "2291",
    "list_language": [],
    "array_tags": [],
    "list_album": [
      {
        "id_album": "63410260",
        "link_thumb": "https://live.staticflickr.com/65535/51787783090_1e3e585453_o.gif",
        "title": "Anime"
      }
    ]
  },
  {
    "author": "vuong234",
    "link_thumb": "https://live.staticflickr.com/65535/51786916116_37a00d3072_o.gif",
    "link_bin": "https://github.com/lmbstudiocontact/mb4_21/raw/main/230.bin",
    "id_bin": "230",
    "list_language": [],
    "array_tags": [
      "date",
      "digital",
      "battery",
      "steps"
    ],
    "list_album": [
      {
        "id_album": "63410260",
        "link_thumb": "https://live.staticflickr.com/65535/51786916116_37a00d3072_o.gif",
        "title": "Anime"
      }
    ]
  },
  {
    "author": "VictorFerNBRAZIL",
    "link_thumb": "https://live.staticflickr.com/65535/51787782955_7482436599_o.gif",
    "link_bin": "https://github.com/lmbstudiocontact/mb4_21/raw/main/2301.bin",
    "id_bin": "2301",
    "list_language": [],
    "array_tags": [
      "digital",
      "english",
      "anime"
    ],
    "list_album": [
      {
        "id_album": "63410260",
        "link_thumb": "https://live.staticflickr.com/65535/51787782955_7482436599_o.gif",
        "title": "Anime"
      }
    ]
  },
  {
    "author": "VictorFerNBRAZIL",
    "link_thumb": "https://live.staticflickr.com/65535/51787782860_d38dcb8815_o.gif",
    "link_bin": "https://github.com/lmbstudiocontact/mb4_21/raw/main/2304.bin",
    "id_bin": "2304",
    "list_language": [],
    "array_tags": [
      "super",
      "ball",
      "goku",
      "english",
      "dragon",
      "anime"
    ],
    "list_album": [
      {
        "id_album": "63410260",
        "link_thumb": "https://live.staticflickr.com/65535/51787782860_d38dcb8815_o.gif",
        "title": "Anime"
      }
    ]
  },
  {
    "author": "VictorFerNBRAZIL",
    "link_thumb": "https://live.staticflickr.com/65535/51787782805_8dfd38fee4_o.gif",
    "link_bin": "https://github.com/lmbstudiocontact/mb4_21/raw/main/2306.bin",
    "id_bin": "2306",
    "list_language": [],
    "array_tags": [
      "naruto",
      "english",
      "anime"
    ],
    "list_album": [
      {
        "id_album": "63410260",
        "link_thumb": "https://live.staticflickr.com/65535/51787782805_8dfd38fee4_o.gif",
        "title": "Anime"
      }
    ]
  },
  {
    "author": "小洪昵称",
    "link_thumb": "https://live.staticflickr.com/65535/51787782780_17355228b2_o.gif",
    "link_bin": "https://github.com/lmbstudiocontact/mb4_21/raw/main/2308.bin",
    "id_bin": "2308",
    "list_language": [],
    "array_tags": [],
    "list_album": [
      {
        "id_album": "63410260",
        "link_thumb": "https://live.staticflickr.com/65535/51787782780_17355228b2_o.gif",
        "title": "Anime"
      }
    ]
  },
  {
    "author": "VictorFerNBRAZIL",
    "link_thumb": "https://live.staticflickr.com/65535/51786092377_a4cf5be2ce_o.gif",
    "link_bin": "https://github.com/lmbstudiocontact/mb4_21/raw/main/2310.bin",
    "id_bin": "2310",
    "list_language": [],
    "array_tags": [
      "english",
      "anime"
    ],
    "list_album": [
      {
        "id_album": "63410260",
        "link_thumb": "https://live.staticflickr.com/65535/51786092377_a4cf5be2ce_o.gif",
        "title": "Anime"
      }
    ]
  },
  {
    "author": "VictorFerNBRAZIL",
    "link_thumb": "https://live.staticflickr.com/65535/51787530344_42a7e9aab8_o.gif",
    "link_bin": "https://github.com/lmbstudiocontact/mb4_21/raw/main/2347.bin",
    "id_bin": "2347",
    "list_language": [],
    "array_tags": [
      "black",
      "english",
      "anime"
    ],
    "list_album": [
      {
        "id_album": "63410260",
        "link_thumb": "https://live.staticflickr.com/65535/51787530344_42a7e9aab8_o.gif",
        "title": "Anime"
      }
    ]
  },
  {
    "author": "SlenderGz",
    "link_thumb": "https://live.staticflickr.com/65535/51786908621_c88c4ca49c_o.gif",
    "link_bin": "https://github.com/lmbstudiocontact/mb4_21/raw/main/2349.bin",
    "id_bin": "2349",
    "list_language": [],
    "array_tags": [
      "girl",
      "anime"
    ],
    "list_album": [
      {
        "id_album": "63410260",
        "link_thumb": "https://live.staticflickr.com/65535/51786908621_c88c4ca49c_o.gif",
        "title": "Anime"
      }
    ]
  },
  {
    "author": "SlenderGz",
    "link_thumb": "https://live.staticflickr.com/65535/51786091397_1b2a3f9e9e_o.gif",
    "link_bin": "https://github.com/lmbstudiocontact/mb4_21/raw/main/2350.bin",
    "id_bin": "2350",
    "list_language": [],
    "array_tags": [
      "girl",
      "anime"
    ],
    "list_album": [
      {
        "id_album": "63410260",
        "link_thumb": "https://live.staticflickr.com/65535/51786091397_1b2a3f9e9e_o.gif",
        "title": "Anime"
      }
    ]
  },
  {
    "author": "SlenderGz",
    "link_thumb": "https://live.staticflickr.com/65535/51787161223_71b306c5b6_o.gif",
    "link_bin": "https://github.com/lmbstudiocontact/mb4_21/raw/main/2351.bin",
    "id_bin": "2351",
    "list_language": [],
    "array_tags": [
      "anime"
    ],
    "list_album": [
      {
        "id_album": "63410260",
        "link_thumb": "https://live.staticflickr.com/65535/51787161223_71b306c5b6_o.gif",
        "title": "Anime"
      }
    ]
  }
]