[
  {
    "author": "Racdsousa",
    "link_thumb": "https://live.staticflickr.com/65535/51786074522_435e5d598f_o.gif",
    "link_bin": "https://github.com/lmbstudiocontact/mb4_16/raw/main/18879.bin",
    "id_bin": "18879",
    "list_language": [],
    "array_tags": [
      "digital",
      "date",
      "distance",
      "heartrate",
      "battery"
    ],
    "list_album": [
      {
        "id_album": "-1956005621",
        "link_thumb": "https://live.staticflickr.com/65535/51786074522_435e5d598f_o.gif",
        "title": "None_2"
      }
    ]
  },
  {
    "author": "Racdsousa",
    "link_thumb": "https://live.staticflickr.com/65535/51787144193_901f62afa4_o.gif",
    "link_bin": "https://github.com/lmbstudiocontact/mb4_16/raw/main/18880.bin",
    "id_bin": "18880",
    "list_language": [],
    "array_tags": [
      "digital",
      "date",
      "distance",
      "heartrate",
      "battery"
    ],
    "list_album": [
      {
        "id_album": "-1956005621",
        "link_thumb": "https://live.staticflickr.com/65535/51787144193_901f62afa4_o.gif",
        "title": "None_2"
      }
    ]
  },
  {
    "author": "selmanc",
    "link_thumb": "https://live.staticflickr.com/65535/51786890986_815f319138_o.gif",
    "link_bin": "https://github.com/lmbstudiocontact/mb4_16/raw/main/18888.bin",
    "id_bin": "18888",
    "list_language": [],
    "array_tags": [
      "date",
      "digital",
      "distance",
      "heartrate",
      "calories",
      "battery",
      "steps",
      "cyan",
      "red",
      "seconds",
      "blue",
      "white"
    ],
    "list_album": [
      {
        "id_album": "-1956005621",
        "link_thumb": "https://live.staticflickr.com/65535/51786890986_815f319138_o.gif",
        "title": "None_2"
      }
    ]
  },
  {
    "author": "selmanc",
    "link_thumb": "https://live.staticflickr.com/65535/51786890961_ce8bb9d86c_o.gif",
    "link_bin": "https://github.com/lmbstudiocontact/mb4_16/raw/main/18889.bin",
    "id_bin": "18889",
    "list_language": [],
    "array_tags": [
      "digital",
      "date",
      "day"
    ],
    "list_album": [
      {
        "id_album": "-1956005621",
        "link_thumb": "https://live.staticflickr.com/65535/51786890961_ce8bb9d86c_o.gif",
        "title": "None_2"
      }
    ]
  },
  {
    "author": "Bryan24352",
    "link_thumb": "https://live.staticflickr.com/65535/51786074267_ca7ee85b65_o.gif",
    "link_bin": "https://github.com/lmbstudiocontact/mb4_16/raw/main/18890.bin",
    "id_bin": "18890",
    "list_language": [],
    "array_tags": [
      "digital",
      "dark",
      "simple",
      "pl"
    ],
    "list_album": [
      {
        "id_album": "-1956005621",
        "link_thumb": "https://live.staticflickr.com/65535/51786074267_ca7ee85b65_o.gif",
        "title": "None_2"
      }
    ]
  },
  {
    "author": "mikerx",
    "link_thumb": "https://live.staticflickr.com/65535/51787763950_3227b17db0_o.gif",
    "link_bin": "https://github.com/lmbstudiocontact/mb4_16/raw/main/18891.bin",
    "id_bin": "18891",
    "list_language": [],
    "array_tags": [
      "date",
      "analog",
      "distance",
      "battery",
      "steps"
    ],
    "list_album": [
      {
        "id_album": "-1956005621",
        "link_thumb": "https://live.staticflickr.com/65535/51787763950_3227b17db0_o.gif",
        "title": "None_2"
      }
    ]
  },
  {
    "author": "gabelegal",
    "link_thumb": "https://live.staticflickr.com/65535/51786890901_3957ce6d34_o.gif",
    "link_bin": "https://github.com/lmbstudiocontact/mb4_16/raw/main/18892.bin",
    "id_bin": "18892",
    "list_language": [],
    "array_tags": [
      "digital",
      "date",
      "battery",
      "steps"
    ],
    "list_album": [
      {
        "id_album": "-1956005621",
        "link_thumb": "https://live.staticflickr.com/65535/51786890901_3957ce6d34_o.gif",
        "title": "None_2"
      }
    ]
  },
  {
    "author": "Bryan24352",
    "link_thumb": "https://live.staticflickr.com/65535/51787512624_28bbee4b8c_o.gif",
    "link_bin": "https://github.com/lmbstudiocontact/mb4_16/raw/main/18893.bin",
    "id_bin": "18893",
    "list_language": [],
    "array_tags": [
      "digital",
      "english",
      "dark",
      "simple"
    ],
    "list_album": [
      {
        "id_album": "-1956005621",
        "link_thumb": "https://live.staticflickr.com/65535/51787512624_28bbee4b8c_o.gif",
        "title": "None_2"
      }
    ]
  },
  {
    "author": "Bryan24352",
    "link_thumb": "https://live.staticflickr.com/65535/51786890866_16dc66f38c_o.gif",
    "link_bin": "https://github.com/lmbstudiocontact/mb4_16/raw/main/18894.bin",
    "id_bin": "18894",
    "list_language": [],
    "array_tags": [
      "digital",
      "dark",
      "simple",
      "pl"
    ],
    "list_album": [
      {
        "id_album": "-1956005621",
        "link_thumb": "https://live.staticflickr.com/65535/51786890866_16dc66f38c_o.gif",
        "title": "None_2"
      }
    ]
  },
  {
    "author": "selmanc",
    "link_thumb": "https://live.staticflickr.com/65535/51786074117_3c5874109b_o.gif",
    "link_bin": "https://github.com/lmbstudiocontact/mb4_16/raw/main/18900.bin",
    "id_bin": "18900",
    "list_language": [],
    "array_tags": [
      "date",
      "digital",
      "heartrate",
      "battery",
      "steps"
    ],
    "list_album": [
      {
        "id_album": "-1956005621",
        "link_thumb": "https://live.staticflickr.com/65535/51786074117_3c5874109b_o.gif",
        "title": "None_2"
      }
    ]
  },
  {
    "author": "Vitor Fernando Elias",
    "link_thumb": "https://live.staticflickr.com/65535/51787143788_96b256761d_o.gif",
    "link_bin": "https://github.com/lmbstudiocontact/mb4_16/raw/main/18903.bin",
    "id_bin": "18903",
    "list_language": [],
    "array_tags": [
      "analog",
      "weather",
      "steps"
    ],
    "list_album": [
      {
        "id_album": "-1956005621",
        "link_thumb": "https://live.staticflickr.com/65535/51787143788_96b256761d_o.gif",
        "title": "None_2"
      }
    ]
  },
  {
    "author": "Bacer",
    "link_thumb": "https://live.staticflickr.com/65535/51787763805_cd7ff59558_o.gif",
    "link_bin": "https://github.com/lmbstudiocontact/mb4_16/raw/main/18905.bin",
    "id_bin": "18905",
    "list_language": [],
    "array_tags": [
      "digital",
      "date",
      "russian",
      "nike",
      "battery"
    ],
    "list_album": [
      {
        "id_album": "-1956005621",
        "link_thumb": "https://live.staticflickr.com/65535/51787763805_cd7ff59558_o.gif",
        "title": "None_2"
      }
    ]
  },
  {
    "author": "oggidm20",
    "link_thumb": "https://live.staticflickr.com/65535/51787143738_5a0faaa2b6_o.gif",
    "link_bin": "https://github.com/lmbstudiocontact/mb4_16/raw/main/18906.bin",
    "id_bin": "18906",
    "list_language": [],
    "array_tags": [
      "marvels"
    ],
    "list_album": [
      {
        "id_album": "-1956005621",
        "link_thumb": "https://live.staticflickr.com/65535/51787143738_5a0faaa2b6_o.gif",
        "title": "None_2"
      }
    ]
  },
  {
    "author": "GabrielWDSA",
    "link_thumb": "https://live.staticflickr.com/65535/51787512459_e2cce4bb5f_o.gif",
    "link_bin": "https://github.com/lmbstudiocontact/mb4_16/raw/main/18907.bin",
    "id_bin": "18907",
    "list_language": [],
    "array_tags": [
      "digital",
      "date",
      "distance",
      "battery",
      "steps"
    ],
    "list_album": [
      {
        "id_album": "-1956005621",
        "link_thumb": "https://live.staticflickr.com/65535/51787512459_e2cce4bb5f_o.gif",
        "title": "None_2"
      }
    ]
  },
  {
    "author": "Rick_TO",
    "link_thumb": "https://live.staticflickr.com/65535/51786073997_31a9698f9b_o.gif",
    "link_bin": "https://github.com/lmbstudiocontact/mb4_16/raw/main/18908.bin",
    "id_bin": "18908",
    "list_language": [],
    "array_tags": [
      "digital",
      "date",
      "seconds",
      "floors",
      "distance",
      "heartrate",
      "calories",
      "battery",
      "steps"
    ],
    "list_album": [
      {
        "id_album": "-1956005621",
        "link_thumb": "https://live.staticflickr.com/65535/51786073997_31a9698f9b_o.gif",
        "title": "None_2"
      }
    ]
  },
  {
    "author": "vanjura",
    "link_thumb": "https://live.staticflickr.com/65535/51787512399_fc8a3bf795_o.gif",
    "link_bin": "https://github.com/lmbstudiocontact/mb4_16/raw/main/18909.bin",
    "id_bin": "18909",
    "list_language": [],
    "array_tags": [
      "digital",
      "date",
      "distance",
      "heartrate",
      "calories",
      "battery",
      "steps"
    ],
    "list_album": [
      {
        "id_album": "-1956005621",
        "link_thumb": "https://live.staticflickr.com/65535/51787512399_fc8a3bf795_o.gif",
        "title": "None_2"
      }
    ]
  },
  {
    "author": "gabelegal",
    "link_thumb": "https://live.staticflickr.com/65535/51786073922_2bdc559f73_o.gif",
    "link_bin": "https://github.com/lmbstudiocontact/mb4_16/raw/main/18910.bin",
    "id_bin": "18910",
    "list_language": [],
    "array_tags": [
      "digital",
      "date",
      "battery"
    ],
    "list_album": [
      {
        "id_album": "-1956005621",
        "link_thumb": "https://live.staticflickr.com/65535/51786073922_2bdc559f73_o.gif",
        "title": "None_2"
      }
    ]
  },
  {
    "author": "gabelegal",
    "link_thumb": "https://live.staticflickr.com/65535/51786073877_f74f26440c_o.gif",
    "link_bin": "https://github.com/lmbstudiocontact/mb4_16/raw/main/18911.bin",
    "id_bin": "18911",
    "list_language": [],
    "array_tags": [
      "digital",
      "date",
      "battery"
    ],
    "list_album": [
      {
        "id_album": "-1956005621",
        "link_thumb": "https://live.staticflickr.com/65535/51786073877_f74f26440c_o.gif",
        "title": "None_2"
      }
    ]
  },
  {
    "author": "GabrielWDSA",
    "link_thumb": "https://live.staticflickr.com/65535/51786073802_c1d2496f40_o.gif",
    "link_bin": "https://github.com/lmbstudiocontact/mb4_16/raw/main/18915.bin",
    "id_bin": "18915",
    "list_language": [],
    "array_tags": [
      "digital",
      "date",
      "distance",
      "calories",
      "battery",
      "steps"
    ],
    "list_album": [
      {
        "id_album": "-1956005621",
        "link_thumb": "https://live.staticflickr.com/65535/51786073802_c1d2496f40_o.gif",
        "title": "None_2"
      }
    ]
  },
  {
    "author": "Artark",
    "link_thumb": "https://live.staticflickr.com/65535/51787143473_0991e43a33_o.gif",
    "link_bin": "https://github.com/lmbstudiocontact/mb4_16/raw/main/18916.bin",
    "id_bin": "18916",
    "list_language": [],
    "array_tags": [
      "digital",
      "date",
      "distance",
      "battery"
    ],
    "list_album": [
      {
        "id_album": "-1956005621",
        "link_thumb": "https://live.staticflickr.com/65535/51787143473_0991e43a33_o.gif",
        "title": "None_2"
      }
    ]
  },
  {
    "author": "Artark",
    "link_thumb": "https://live.staticflickr.com/65535/51786073752_5f2d29e882_o.gif",
    "link_bin": "https://github.com/lmbstudiocontact/mb4_16/raw/main/18917.bin",
    "id_bin": "18917",
    "list_language": [],
    "array_tags": [
      "digital",
      "date",
      "distance",
      "battery"
    ],
    "list_album": [
      {
        "id_album": "-1956005621",
        "link_thumb": "https://live.staticflickr.com/65535/51786073752_5f2d29e882_o.gif",
        "title": "None_2"
      }
    ]
  },
  {
    "author": "GabrielWDSA",
    "link_thumb": "https://live.staticflickr.com/65535/51787512144_ba3e7ce84f_o.gif",
    "link_bin": "https://github.com/lmbstudiocontact/mb4_16/raw/main/18918.bin",
    "id_bin": "18918",
    "list_language": [],
    "array_tags": [
      "digital",
      "battery",
      "steps"
    ],
    "list_album": [
      {
        "id_album": "-1956005621",
        "link_thumb": "https://live.staticflickr.com/65535/51787512144_ba3e7ce84f_o.gif",
        "title": "None_2"
      }
    ]
  },
  {
    "author": "Bacer",
    "link_thumb": "https://live.staticflickr.com/65535/51786890471_9fcb9773a0_o.gif",
    "link_bin": "https://github.com/lmbstudiocontact/mb4_16/raw/main/18920.bin",
    "id_bin": "18920",
    "list_language": [],
    "array_tags": [
      "digital",
      "date",
      "russian",
      "nike"
    ],
    "list_album": [
      {
        "id_album": "-1956005621",
        "link_thumb": "https://live.staticflickr.com/65535/51786890471_9fcb9773a0_o.gif",
        "title": "None_2"
      }
    ]
  },
  {
    "author": "italopoca",
    "link_thumb": "https://live.staticflickr.com/65535/51787763420_6699595327_o.gif",
    "link_bin": "https://github.com/lmbstudiocontact/mb4_16/raw/main/18922.bin",
    "id_bin": "18922",
    "list_language": [],
    "array_tags": [
      "games"
    ],
    "list_album": [
      {
        "id_album": "-1956005621",
        "link_thumb": "https://live.staticflickr.com/65535/51787763420_6699595327_o.gif",
        "title": "None_2"
      }
    ]
  },
  {
    "author": "Wuka",
    "link_thumb": "https://live.staticflickr.com/65535/51787512059_ab686e587d_o.gif",
    "link_bin": "https://github.com/lmbstudiocontact/mb4_16/raw/main/18923.bin",
    "id_bin": "18923",
    "list_language": [],
    "array_tags": [
      "fallout",
      "polski",
      "batman"
    ],
    "list_album": [
      {
        "id_album": "-1956005621",
        "link_thumb": "https://live.staticflickr.com/65535/51787512059_ab686e587d_o.gif",
        "title": "None_2"
      }
    ]
  },
  {
    "author": "miqito",
    "link_thumb": "https://live.staticflickr.com/65535/51787143298_ba491b994b_o.gif",
    "link_bin": "https://github.com/lmbstudiocontact/mb4_16/raw/main/18924.bin",
    "id_bin": "18924",
    "list_language": [],
    "array_tags": [
      "digital",
      "date",
      "steps"
    ],
    "list_album": [
      {
        "id_album": "-1956005621",
        "link_thumb": "https://live.staticflickr.com/65535/51787143298_ba491b994b_o.gif",
        "title": "None_2"
      }
    ]
  },
  {
    "author": "duelago",
    "link_thumb": "https://live.staticflickr.com/65535/51786890376_14a5705d39_o.gif",
    "link_bin": "https://github.com/lmbstudiocontact/mb4_16/raw/main/18925.bin",
    "id_bin": "18925",
    "list_language": [],
    "array_tags": [
      "date",
      "simple",
      "time",
      "steps",
      "day"
    ],
    "list_album": [
      {
        "id_album": "-1956005621",
        "link_thumb": "https://live.staticflickr.com/65535/51786890376_14a5705d39_o.gif",
        "title": "None_2"
      }
    ]
  },
  {
    "author": "5mustafa",
    "link_thumb": "https://live.staticflickr.com/65535/51787763315_172d4d246c_o.gif",
    "link_bin": "https://github.com/lmbstudiocontact/mb4_16/raw/main/18937.bin",
    "id_bin": "18937",
    "list_language": [],
    "array_tags": [
      "date",
      "digital",
      "seconds",
      "distance",
      "heartrate",
      "calories",
      "battery",
      "steps"
    ],
    "list_album": [
      {
        "id_album": "-1956005621",
        "link_thumb": "https://live.staticflickr.com/65535/51787763315_172d4d246c_o.gif",
        "title": "None_2"
      }
    ]
  },
  {
    "author": "5mustafa",
    "link_thumb": "https://live.staticflickr.com/65535/51787143228_66e0e5c65e_o.gif",
    "link_bin": "https://github.com/lmbstudiocontact/mb4_16/raw/main/18938.bin",
    "id_bin": "18938",
    "list_language": [],
    "array_tags": [
      "digital",
      "date",
      "seconds",
      "distance",
      "heartrate",
      "calories",
      "battery",
      "steps"
    ],
    "list_album": [
      {
        "id_album": "-1956005621",
        "link_thumb": "https://live.staticflickr.com/65535/51787143228_66e0e5c65e_o.gif",
        "title": "None_2"
      }
    ]
  },
  {
    "author": "marcioc.ribeiro",
    "link_thumb": "https://live.staticflickr.com/65535/51786890286_e064743792_o.gif",
    "link_bin": "https://github.com/lmbstudiocontact/mb4_16/raw/main/18942.bin",
    "id_bin": "18942",
    "list_language": [],
    "array_tags": [
      "digital",
      "date",
      "analog",
      "heartrate",
      "battery",
      "steps"
    ],
    "list_album": [
      {
        "id_album": "-1956005621",
        "link_thumb": "https://live.staticflickr.com/65535/51786890286_e064743792_o.gif",
        "title": "None_2"
      }
    ]
  },
  {
    "author": "mikerx",
    "link_thumb": "https://live.staticflickr.com/65535/51786890251_164219cbe2_o.gif",
    "link_bin": "https://github.com/lmbstudiocontact/mb4_16/raw/main/18943.bin",
    "id_bin": "18943",
    "list_language": [],
    "array_tags": [
      "date",
      "analog",
      "white",
      "distance",
      "clock",
      "battery",
      "steps"
    ],
    "list_album": [
      {
        "id_album": "-1956005621",
        "link_thumb": "https://live.staticflickr.com/65535/51786890251_164219cbe2_o.gif",
        "title": "None_2"
      }
    ]
  },
  {
    "author": "Racdsousa",
    "link_thumb": "https://live.staticflickr.com/65535/51787143163_0b1696fa3e_o.gif",
    "link_bin": "https://github.com/lmbstudiocontact/mb4_16/raw/main/18944.bin",
    "id_bin": "18944",
    "list_language": [],
    "array_tags": [
      "digital",
      "date",
      "battery",
      "steps"
    ],
    "list_album": [
      {
        "id_album": "-1956005621",
        "link_thumb": "https://live.staticflickr.com/65535/51787143163_0b1696fa3e_o.gif",
        "title": "None_2"
      }
    ]
  },
  {
    "author": "gabrielqwe022",
    "link_thumb": "https://live.staticflickr.com/65535/51786073447_67c09043e5_o.gif",
    "link_bin": "https://github.com/lmbstudiocontact/mb4_16/raw/main/18954.bin",
    "id_bin": "18954",
    "list_language": [],
    "array_tags": [
      "digital",
      "distance",
      "calories",
      "battery",
      "day"
    ],
    "list_album": [
      {
        "id_album": "-1956005621",
        "link_thumb": "https://live.staticflickr.com/65535/51786073447_67c09043e5_o.gif",
        "title": "None_2"
      }
    ]
  },
  {
    "author": "toxicsquall",
    "link_thumb": "https://live.staticflickr.com/65535/51787511849_b03027395b_o.gif",
    "link_bin": "https://github.com/lmbstudiocontact/mb4_16/raw/main/18956.bin",
    "id_bin": "18956",
    "list_language": [],
    "array_tags": [
      "digital",
      "date",
      "nintendo",
      "pokemon",
      "games",
      "battery",
      "steps"
    ],
    "list_album": [
      {
        "id_album": "-1956005621",
        "link_thumb": "https://live.staticflickr.com/65535/51787511849_b03027395b_o.gif",
        "title": "None_2"
      }
    ]
  },
  {
    "author": "Medozavr",
    "link_thumb": "https://live.staticflickr.com/65535/51787143053_496b059e46_o.gif",
    "link_bin": "https://github.com/lmbstudiocontact/mb4_16/raw/main/18960.bin",
    "id_bin": "18960",
    "list_language": [],
    "array_tags": [
      "neon",
      "retro",
      "animation"
    ],
    "list_album": [
      {
        "id_album": "-1956005621",
        "link_thumb": "https://live.staticflickr.com/65535/51787143053_496b059e46_o.gif",
        "title": "None_2"
      }
    ]
  },
  {
    "author": "Ziyaeray",
    "link_thumb": "https://live.staticflickr.com/65535/51787143028_8ec25bbb7c_o.gif",
    "link_bin": "https://github.com/lmbstudiocontact/mb4_16/raw/main/18961.bin",
    "id_bin": "18961",
    "list_language": [],
    "array_tags": [
      "digital",
      "date",
      "neon",
      "battery"
    ],
    "list_album": [
      {
        "id_album": "-1956005621",
        "link_thumb": "https://live.staticflickr.com/65535/51787143028_8ec25bbb7c_o.gif",
        "title": "None_2"
      }
    ]
  },
  {
    "author": "cvg8",
    "link_thumb": "https://live.staticflickr.com/65535/51787763070_5a4d65d8cf_o.gif",
    "link_bin": "https://github.com/lmbstudiocontact/mb4_16/raw/main/18963.bin",
    "id_bin": "18963",
    "list_language": [],
    "array_tags": [
      "date",
      "digital",
      "big",
      "nike",
      "semana",
      "simple",
      "minimalista",
      "fecha",
      "minimal",
      "blue",
      "logo",
      "azul"
    ],
    "list_album": [
      {
        "id_album": "-1956005621",
        "link_thumb": "https://live.staticflickr.com/65535/51787763070_5a4d65d8cf_o.gif",
        "title": "None_2"
      }
    ]
  },
  {
    "author": "Brawl Stars",
    "link_thumb": "https://live.staticflickr.com/65535/51787511764_49d28193ce_o.gif",
    "link_bin": "https://github.com/lmbstudiocontact/mb4_16/raw/main/18964.bin",
    "id_bin": "18964",
    "list_language": [],
    "array_tags": [
      "digital",
      "date",
      "seconds",
      "distance",
      "heartrate",
      "battery"
    ],
    "list_album": [
      {
        "id_album": "-1956005621",
        "link_thumb": "https://live.staticflickr.com/65535/51787511764_49d28193ce_o.gif",
        "title": "None_2"
      }
    ]
  },
  {
    "author": "z88487561",
    "link_thumb": "https://live.staticflickr.com/65535/51787142983_047cfe9a41_o.gif",
    "link_bin": "https://github.com/lmbstudiocontact/mb4_16/raw/main/18970.bin",
    "id_bin": "18970",
    "list_language": [],
    "array_tags": [
      "digital"
    ],
    "list_album": [
      {
        "id_album": "-1956005621",
        "link_thumb": "https://live.staticflickr.com/65535/51787142983_047cfe9a41_o.gif",
        "title": "None_2"
      }
    ]
  },
  {
    "author": "zapa360",
    "link_thumb": "https://live.staticflickr.com/65535/51787142978_61e5920da9_o.gif",
    "link_bin": "https://github.com/lmbstudiocontact/mb4_16/raw/main/18971.bin",
    "id_bin": "18971",
    "list_language": [],
    "array_tags": [],
    "list_album": [
      {
        "id_album": "-1956005621",
        "link_thumb": "https://live.staticflickr.com/65535/51787142978_61e5920da9_o.gif",
        "title": "None_2"
      }
    ]
  },
  {
    "author": "Brawl Stars",
    "link_thumb": "https://live.staticflickr.com/65535/51787142958_5526ed6378_o.gif",
    "link_bin": "https://github.com/lmbstudiocontact/mb4_16/raw/main/18972.bin",
    "id_bin": "18972",
    "list_language": [],
    "array_tags": [
      "digital",
      "date",
      "analog",
      "seconds",
      "floors",
      "distance",
      "heartrate",
      "weather",
      "calories",
      "battery",
      "steps"
    ],
    "list_album": [
      {
        "id_album": "-1956005621",
        "link_thumb": "https://live.staticflickr.com/65535/51787142958_5526ed6378_o.gif",
        "title": "None_2"
      }
    ]
  },
  {
    "author": "Vonamor",
    "link_thumb": "https://live.staticflickr.com/65535/51787762940_51fc3e0450_o.gif",
    "link_bin": "https://github.com/lmbstudiocontact/mb4_16/raw/main/18973.bin",
    "id_bin": "18973",
    "list_language": [],
    "array_tags": [
      "digital",
      "music"
    ],
    "list_album": [
      {
        "id_album": "-1956005621",
        "link_thumb": "https://live.staticflickr.com/65535/51787762940_51fc3e0450_o.gif",
        "title": "None_2"
      }
    ]
  },
  {
    "author": "Phremswa2",
    "link_thumb": "https://live.staticflickr.com/65535/51787511614_9cb30591d8_o.gif",
    "link_bin": "https://github.com/lmbstudiocontact/mb4_16/raw/main/18974.bin",
    "id_bin": "18974",
    "list_language": [],
    "array_tags": [
      "digital",
      "heartrate",
      "battery"
    ],
    "list_album": [
      {
        "id_album": "-1956005621",
        "link_thumb": "https://live.staticflickr.com/65535/51787511614_9cb30591d8_o.gif",
        "title": "None_2"
      }
    ]
  },
  {
    "author": "icici",
    "link_thumb": "https://live.staticflickr.com/65535/51786889886_0ffef62acf_o.gif",
    "link_bin": "https://github.com/lmbstudiocontact/mb4_16/raw/main/18977.bin",
    "id_bin": "18977",
    "list_language": [],
    "array_tags": [
      "floors",
      "calories"
    ],
    "list_album": [
      {
        "id_album": "-1956005621",
        "link_thumb": "https://live.staticflickr.com/65535/51786889886_0ffef62acf_o.gif",
        "title": "None_2"
      }
    ]
  },
  {
    "author": "Ginx12",
    "link_thumb": "https://live.staticflickr.com/65535/51787142848_b59e3ee289_o.gif",
    "link_bin": "https://github.com/lmbstudiocontact/mb4_16/raw/main/18979.bin",
    "id_bin": "18979",
    "list_language": [],
    "array_tags": [
      "date",
      "steps"
    ],
    "list_album": [
      {
        "id_album": "-1956005621",
        "link_thumb": "https://live.staticflickr.com/65535/51787142848_b59e3ee289_o.gif",
        "title": "None_2"
      }
    ]
  },
  {
    "author": "icici",
    "link_thumb": "https://live.staticflickr.com/65535/51787511529_13cf5be70b_o.gif",
    "link_bin": "https://github.com/lmbstudiocontact/mb4_16/raw/main/18984.bin",
    "id_bin": "18984",
    "list_language": [],
    "array_tags": [
      "date",
      "floors"
    ],
    "list_album": [
      {
        "id_album": "-1956005621",
        "link_thumb": "https://live.staticflickr.com/65535/51787511529_13cf5be70b_o.gif",
        "title": "None_2"
      }
    ]
  },
  {
    "author": "davidssound",
    "link_thumb": "https://live.staticflickr.com/65535/51787142808_3e7edf9d7f_o.gif",
    "link_bin": "https://github.com/lmbstudiocontact/mb4_16/raw/main/18985.bin",
    "id_bin": "18985",
    "list_language": [],
    "array_tags": [
      "digital",
      "heartrate",
      "battery",
      "steps"
    ],
    "list_album": [
      {
        "id_album": "-1956005621",
        "link_thumb": "https://live.staticflickr.com/65535/51787142808_3e7edf9d7f_o.gif",
        "title": "None_2"
      }
    ]
  },
  {
    "author": "SandraMichael",
    "link_thumb": "https://live.staticflickr.com/65535/51786073097_dfa86fe21b_o.gif",
    "link_bin": "https://github.com/lmbstudiocontact/mb4_16/raw/main/18987.bin",
    "id_bin": "18987",
    "list_language": [],
    "array_tags": [
      "digital"
    ],
    "list_album": [
      {
        "id_album": "-1956005621",
        "link_thumb": "https://live.staticflickr.com/65535/51786073097_dfa86fe21b_o.gif",
        "title": "None_2"
      }
    ]
  },
  {
    "author": "SandraMichael",
    "link_thumb": "https://live.staticflickr.com/65535/51787762735_20f0e61f3e_o.gif",
    "link_bin": "https://github.com/lmbstudiocontact/mb4_16/raw/main/18988.bin",
    "id_bin": "18988",
    "list_language": [],
    "array_tags": [
      "digital",
      "seconds"
    ],
    "list_album": [
      {
        "id_album": "-1956005621",
        "link_thumb": "https://live.staticflickr.com/65535/51787762735_20f0e61f3e_o.gif",
        "title": "None_2"
      }
    ]
  },
  {
    "author": "CrowDec",
    "link_thumb": "https://live.staticflickr.com/65535/51786073027_63d53cc26e_o.gif",
    "link_bin": "https://github.com/lmbstudiocontact/mb4_16/raw/main/18989.bin",
    "id_bin": "18989",
    "list_language": [],
    "array_tags": [
      "digital",
      "date",
      "distance",
      "heartrate",
      "weather",
      "calories",
      "battery",
      "steps"
    ],
    "list_album": [
      {
        "id_album": "-1956005621",
        "link_thumb": "https://live.staticflickr.com/65535/51786073027_63d53cc26e_o.gif",
        "title": "None_2"
      }
    ]
  }
]