[
  {
    "author": "LluisQuilez",
    "link_thumb": "https://live.staticflickr.com/65535/51787758205_2cba1057d9_o.gif",
    "link_bin": "https://github.com/lmbstudiocontact/mb4_16/raw/main/16051.bin",
    "id_bin": "16051",
    "list_language": [],
    "array_tags": [
      "digital",
      "bateria",
      "bluetooth",
      "pulse",
      "lcd",
      "steps",
      "pasos"
    ],
    "list_album": [
      {
        "id_album": "-1956005621",
        "link_thumb": "https://live.staticflickr.com/65535/51787758205_2cba1057d9_o.gif",
        "title": "None_2"
      }
    ]
  },
  {
    "author": ".Kosmik",
    "link_thumb": "https://live.staticflickr.com/65535/51787758180_7fe9539edf_o.gif",
    "link_bin": "https://github.com/lmbstudiocontact/mb4_16/raw/main/16052.bin",
    "id_bin": "16052",
    "list_language": [],
    "array_tags": [
      "digital",
      "date",
      "heartrate",
      "battery",
      "steps"
    ],
    "list_album": [
      {
        "id_album": "-1956005621",
        "link_thumb": "https://live.staticflickr.com/65535/51787758180_7fe9539edf_o.gif",
        "title": "None_2"
      }
    ]
  },
  {
    "author": ".Kosmik",
    "link_thumb": "https://live.staticflickr.com/65535/51787138413_2ccf529ce0_o.gif",
    "link_bin": "https://github.com/lmbstudiocontact/mb4_16/raw/main/16053.bin",
    "id_bin": "16053",
    "list_language": [],
    "array_tags": [
      "date",
      "analog",
      "heartrate",
      "battery",
      "steps"
    ],
    "list_album": [
      {
        "id_album": "-1956005621",
        "link_thumb": "https://live.staticflickr.com/65535/51787138413_2ccf529ce0_o.gif",
        "title": "None_2"
      }
    ]
  },
  {
    "author": ".Kosmik",
    "link_thumb": "https://live.staticflickr.com/65535/51786885136_b2695d3927_o.gif",
    "link_bin": "https://github.com/lmbstudiocontact/mb4_16/raw/main/16055.bin",
    "id_bin": "16055",
    "list_language": [],
    "array_tags": [
      "digital",
      "date",
      "battery",
      "steps"
    ],
    "list_album": [
      {
        "id_album": "-1956005621",
        "link_thumb": "https://live.staticflickr.com/65535/51786885136_b2695d3927_o.gif",
        "title": "None_2"
      }
    ]
  },
  {
    "author": ".Kosmik",
    "link_thumb": "https://live.staticflickr.com/65535/51787138338_3fa47e38c6_o.gif",
    "link_bin": "https://github.com/lmbstudiocontact/mb4_16/raw/main/16056.bin",
    "id_bin": "16056",
    "list_language": [],
    "array_tags": [
      "digital",
      "date",
      "distance",
      "heartrate",
      "battery",
      "steps"
    ],
    "list_album": [
      {
        "id_album": "-1956005621",
        "link_thumb": "https://live.staticflickr.com/65535/51787138338_3fa47e38c6_o.gif",
        "title": "None_2"
      }
    ]
  },
  {
    "author": "akhmalcapcom",
    "link_thumb": "https://live.staticflickr.com/65535/51786885111_a37b784f43_o.gif",
    "link_bin": "https://github.com/lmbstudiocontact/mb4_16/raw/main/16057.bin",
    "id_bin": "16057",
    "list_language": [],
    "array_tags": [
      "spiderman",
      "cute"
    ],
    "list_album": [
      {
        "id_album": "-1956005621",
        "link_thumb": "https://live.staticflickr.com/65535/51786885111_a37b784f43_o.gif",
        "title": "None_2"
      }
    ]
  },
  {
    "author": "FRZNGLSRBM",
    "link_thumb": "https://live.staticflickr.com/65535/51787758015_faf4f40c8a_o.gif",
    "link_bin": "https://github.com/lmbstudiocontact/mb4_16/raw/main/16058.bin",
    "id_bin": "16058",
    "list_language": [],
    "array_tags": [
      "digital",
      "seconds"
    ],
    "list_album": [
      {
        "id_album": "-1956005621",
        "link_thumb": "https://live.staticflickr.com/65535/51787758015_faf4f40c8a_o.gif",
        "title": "None_2"
      }
    ]
  },
  {
    "author": "akhmalcapcom",
    "link_thumb": "https://live.staticflickr.com/65535/51787757970_93ac254cb6_o.gif",
    "link_bin": "https://github.com/lmbstudiocontact/mb4_16/raw/main/16059.bin",
    "id_bin": "16059",
    "list_language": [],
    "array_tags": [
      "pokemon",
      "animated",
      "cute",
      "animation"
    ],
    "list_album": [
      {
        "id_album": "-1956005621",
        "link_thumb": "https://live.staticflickr.com/65535/51787757970_93ac254cb6_o.gif",
        "title": "None_2"
      }
    ]
  },
  {
    "author": "cvg8",
    "link_thumb": "https://live.staticflickr.com/65535/51786068202_802aec2d03_o.gif",
    "link_bin": "https://github.com/lmbstudiocontact/mb4_16/raw/main/16060.bin",
    "id_bin": "16060",
    "list_language": [],
    "array_tags": [
      "pink",
      "blue",
      "azul",
      "rosa"
    ],
    "list_album": [
      {
        "id_album": "-1956005621",
        "link_thumb": "https://live.staticflickr.com/65535/51786068202_802aec2d03_o.gif",
        "title": "None_2"
      }
    ]
  },
  {
    "author": "franluciani",
    "link_thumb": "https://live.staticflickr.com/65535/51786884946_dd57750b3b_o.gif",
    "link_bin": "https://github.com/lmbstudiocontact/mb4_16/raw/main/16063.bin",
    "id_bin": "16063",
    "list_language": [],
    "array_tags": [
      "digital",
      "analog",
      "week",
      "month",
      "day"
    ],
    "list_album": [
      {
        "id_album": "-1956005621",
        "link_thumb": "https://live.staticflickr.com/65535/51786884946_dd57750b3b_o.gif",
        "title": "None_2"
      }
    ]
  },
  {
    "author": "+M4rc0",
    "link_thumb": "https://live.staticflickr.com/65535/51786884926_b49e7c9b04_o.gif",
    "link_bin": "https://github.com/lmbstudiocontact/mb4_16/raw/main/16064.bin",
    "id_bin": "16064",
    "list_language": [],
    "array_tags": [
      "digital",
      "battery",
      "steps"
    ],
    "list_album": [
      {
        "id_album": "-1956005621",
        "link_thumb": "https://live.staticflickr.com/65535/51786884926_b49e7c9b04_o.gif",
        "title": "None_2"
      }
    ]
  },
  {
    "author": "toxicsquall",
    "link_thumb": "https://live.staticflickr.com/65535/51787506579_065b79d73e_o.gif",
    "link_bin": "https://github.com/lmbstudiocontact/mb4_16/raw/main/16067.bin",
    "id_bin": "16067",
    "list_language": [],
    "array_tags": [
      "digital",
      "date",
      "pokemon",
      "games",
      "animated",
      "battery",
      "gameboy"
    ],
    "list_album": [
      {
        "id_album": "-1956005621",
        "link_thumb": "https://live.staticflickr.com/65535/51787506579_065b79d73e_o.gif",
        "title": "None_2"
      }
    ]
  },
  {
    "author": "toxicsquall",
    "link_thumb": "https://live.staticflickr.com/65535/51787138003_af21ffcac7_o.gif",
    "link_bin": "https://github.com/lmbstudiocontact/mb4_16/raw/main/16068.bin",
    "id_bin": "16068",
    "list_language": [],
    "array_tags": [
      "digital",
      "game",
      "pokemon",
      "battery"
    ],
    "list_album": [
      {
        "id_album": "-1956005621",
        "link_thumb": "https://live.staticflickr.com/65535/51787138003_af21ffcac7_o.gif",
        "title": "None_2"
      }
    ]
  },
  {
    "author": "Israel_Felixx",
    "link_thumb": "https://live.staticflickr.com/65535/51786884861_bf8fcdf776_o.gif",
    "link_bin": "https://github.com/lmbstudiocontact/mb4_16/raw/main/16069.bin",
    "id_bin": "16069",
    "list_language": [],
    "array_tags": [
      "digital",
      "date",
      "distance",
      "calories",
      "battery",
      "steps"
    ],
    "list_album": [
      {
        "id_album": "-1956005621",
        "link_thumb": "https://live.staticflickr.com/65535/51786884861_bf8fcdf776_o.gif",
        "title": "None_2"
      }
    ]
  },
  {
    "author": "CzAlien",
    "link_thumb": "https://live.staticflickr.com/65535/51787506484_e08df543cf_o.gif",
    "link_bin": "https://github.com/lmbstudiocontact/mb4_16/raw/main/16071.bin",
    "id_bin": "16071",
    "list_language": [],
    "array_tags": [
      "date",
      "digital",
      "cz",
      "battery",
      "steps"
    ],
    "list_album": [
      {
        "id_album": "-1956005621",
        "link_thumb": "https://live.staticflickr.com/65535/51787506484_e08df543cf_o.gif",
        "title": "None_2"
      }
    ]
  },
  {
    "author": "Counterbalance",
    "link_thumb": "https://live.staticflickr.com/65535/51786067927_4d62f79f5a_o.gif",
    "link_bin": "https://github.com/lmbstudiocontact/mb4_16/raw/main/16074.bin",
    "id_bin": "16074",
    "list_language": [],
    "array_tags": [
      "date",
      "digital",
      "seconds",
      "distance",
      "heartrate",
      "calories",
      "time",
      "battery",
      "steps"
    ],
    "list_album": [
      {
        "id_album": "-1956005621",
        "link_thumb": "https://live.staticflickr.com/65535/51786067927_4d62f79f5a_o.gif",
        "title": "None_2"
      }
    ]
  },
  {
    "author": "grazi_andrad",
    "link_thumb": "https://live.staticflickr.com/65535/51786884731_0e02ed9a54_o.gif",
    "link_bin": "https://github.com/lmbstudiocontact/mb4_16/raw/main/16077.bin",
    "id_bin": "16077",
    "list_language": [],
    "array_tags": [
      "digital",
      "date",
      "battery"
    ],
    "list_album": [
      {
        "id_album": "-1956005621",
        "link_thumb": "https://live.staticflickr.com/65535/51786884731_0e02ed9a54_o.gif",
        "title": "None_2"
      }
    ]
  },
  {
    "author": "grazi_andrad",
    "link_thumb": "https://live.staticflickr.com/65535/51787757575_00899aedea_o.gif",
    "link_bin": "https://github.com/lmbstudiocontact/mb4_16/raw/main/16078.bin",
    "id_bin": "16078",
    "list_language": [],
    "array_tags": [
      "bateria",
      "data",
      "passos"
    ],
    "list_album": [
      {
        "id_album": "-1956005621",
        "link_thumb": "https://live.staticflickr.com/65535/51787757575_00899aedea_o.gif",
        "title": "None_2"
      }
    ]
  },
  {
    "author": "Artark",
    "link_thumb": "https://live.staticflickr.com/65535/51787506284_9e6fbb7156_o.gif",
    "link_bin": "https://github.com/lmbstudiocontact/mb4_16/raw/main/16080.bin",
    "id_bin": "16080",
    "list_language": [],
    "array_tags": [
      "digital",
      "distance",
      "battery"
    ],
    "list_album": [
      {
        "id_album": "-1956005621",
        "link_thumb": "https://live.staticflickr.com/65535/51787506284_9e6fbb7156_o.gif",
        "title": "None_2"
      }
    ]
  },
  {
    "author": "shymik",
    "link_thumb": "https://live.staticflickr.com/65535/51786884646_3cffa34aa4_o.gif",
    "link_bin": "https://github.com/lmbstudiocontact/mb4_16/raw/main/16081.bin",
    "id_bin": "16081",
    "list_language": [],
    "array_tags": [
      "digital",
      "date",
      "heartrate",
      "battery",
      "steps"
    ],
    "list_album": [
      {
        "id_album": "-1956005621",
        "link_thumb": "https://live.staticflickr.com/65535/51786884646_3cffa34aa4_o.gif",
        "title": "None_2"
      }
    ]
  },
  {
    "author": "CzAlien",
    "link_thumb": "https://live.staticflickr.com/65535/51786067767_95a5e45d64_o.gif",
    "link_bin": "https://github.com/lmbstudiocontact/mb4_16/raw/main/16083.bin",
    "id_bin": "16083",
    "list_language": [],
    "array_tags": [
      "digital",
      "date",
      "distance",
      "heartrate",
      "cz",
      "calories",
      "battery",
      "pl",
      "steps"
    ],
    "list_album": [
      {
        "id_album": "-1956005621",
        "link_thumb": "https://live.staticflickr.com/65535/51786067767_95a5e45d64_o.gif",
        "title": "None_2"
      }
    ]
  },
  {
    "author": "Mcky0709",
    "link_thumb": "https://live.staticflickr.com/65535/51786067752_e9232845bb_o.gif",
    "link_bin": "https://github.com/lmbstudiocontact/mb4_16/raw/main/16084.bin",
    "id_bin": "16084",
    "list_language": [],
    "array_tags": [
      "digital",
      "love",
      "date",
      "distance",
      "italian",
      "stars",
      "girl",
      "battery",
      "steps",
      "heart",
      "analog",
      "fecha",
      "italiano",
      "pasos"
    ],
    "list_album": [
      {
        "id_album": "-1956005621",
        "link_thumb": "https://live.staticflickr.com/65535/51786067752_e9232845bb_o.gif",
        "title": "None_2"
      }
    ]
  },
  {
    "author": ".Kosmik",
    "link_thumb": "https://live.staticflickr.com/65535/51786067707_53d423c492_o.gif",
    "link_bin": "https://github.com/lmbstudiocontact/mb4_16/raw/main/16085.bin",
    "id_bin": "16085",
    "list_language": [],
    "array_tags": [
      "date",
      "analog",
      "seconds",
      "heartrate",
      "battery",
      "steps"
    ],
    "list_album": [
      {
        "id_album": "-1956005621",
        "link_thumb": "https://live.staticflickr.com/65535/51786067707_53d423c492_o.gif",
        "title": "None_2"
      }
    ]
  },
  {
    "author": "cvg8",
    "link_thumb": "https://live.staticflickr.com/65535/51786067692_63c1a442af_o.gif",
    "link_bin": "https://github.com/lmbstudiocontact/mb4_16/raw/main/16087.bin",
    "id_bin": "16087",
    "list_language": [],
    "array_tags": [
      "moon",
      "blue",
      "azul"
    ],
    "list_album": [
      {
        "id_album": "-1956005621",
        "link_thumb": "https://live.staticflickr.com/65535/51786067692_63c1a442af_o.gif",
        "title": "None_2"
      }
    ]
  },
  {
    "author": "toxicsquall",
    "link_thumb": "https://live.staticflickr.com/65535/51786884491_6ec2103b3e_o.gif",
    "link_bin": "https://github.com/lmbstudiocontact/mb4_16/raw/main/16088.bin",
    "id_bin": "16088",
    "list_language": [],
    "array_tags": [
      "digital",
      "date",
      "game",
      "pokemon",
      "heartrate",
      "battery"
    ],
    "list_album": [
      {
        "id_album": "-1956005621",
        "link_thumb": "https://live.staticflickr.com/65535/51786884491_6ec2103b3e_o.gif",
        "title": "None_2"
      }
    ]
  },
  {
    "author": "LluisQuilez",
    "link_thumb": "https://live.staticflickr.com/65535/51787137593_c2fabe6ea9_o.gif",
    "link_bin": "https://github.com/lmbstudiocontact/mb4_16/raw/main/16089.bin",
    "id_bin": "16089",
    "list_language": [],
    "array_tags": [
      "digital",
      "bateria",
      "pulse",
      "steps",
      "pasos"
    ],
    "list_album": [
      {
        "id_album": "-1956005621",
        "link_thumb": "https://live.staticflickr.com/65535/51787137593_c2fabe6ea9_o.gif",
        "title": "None_2"
      }
    ]
  },
  {
    "author": "mikerx",
    "link_thumb": "https://live.staticflickr.com/65535/51787137563_e9f106490e_o.gif",
    "link_bin": "https://github.com/lmbstudiocontact/mb4_16/raw/main/16090.bin",
    "id_bin": "16090",
    "list_language": [],
    "array_tags": [
      "red",
      "analog",
      "clock"
    ],
    "list_album": [
      {
        "id_album": "-1956005621",
        "link_thumb": "https://live.staticflickr.com/65535/51787137563_e9f106490e_o.gif",
        "title": "None_2"
      }
    ]
  },
  {
    "author": "giovacco",
    "link_thumb": "https://live.staticflickr.com/65535/51786884381_01cca6656c_o.gif",
    "link_bin": "https://github.com/lmbstudiocontact/mb4_16/raw/main/16093.bin",
    "id_bin": "16093",
    "list_language": [],
    "array_tags": [
      "date",
      "analog",
      "white",
      "black",
      "clock"
    ],
    "list_album": [
      {
        "id_album": "-1956005621",
        "link_thumb": "https://live.staticflickr.com/65535/51786884381_01cca6656c_o.gif",
        "title": "None_2"
      }
    ]
  },
  {
    "author": "grazi_andrad",
    "link_thumb": "https://live.staticflickr.com/65535/51787505949_dd3fa85d8e_o.gif",
    "link_bin": "https://github.com/lmbstudiocontact/mb4_16/raw/main/16094.bin",
    "id_bin": "16094",
    "list_language": [],
    "array_tags": [
      "digital",
      "bateria",
      "spiderman",
      "passos"
    ],
    "list_album": [
      {
        "id_album": "-1956005621",
        "link_thumb": "https://live.staticflickr.com/65535/51787505949_dd3fa85d8e_o.gif",
        "title": "None_2"
      }
    ]
  },
  {
    "author": ".Kosmik",
    "link_thumb": "https://live.staticflickr.com/65535/51787505934_9877c9f421_o.gif",
    "link_bin": "https://github.com/lmbstudiocontact/mb4_16/raw/main/16096.bin",
    "id_bin": "16096",
    "list_language": [],
    "array_tags": [
      "digital",
      "battery"
    ],
    "list_album": [
      {
        "id_album": "-1956005621",
        "link_thumb": "https://live.staticflickr.com/65535/51787505934_9877c9f421_o.gif",
        "title": "None_2"
      }
    ]
  },
  {
    "author": "shymik",
    "link_thumb": "https://live.staticflickr.com/65535/51787505874_a5dae981fe_o.gif",
    "link_bin": "https://github.com/lmbstudiocontact/mb4_16/raw/main/16097.bin",
    "id_bin": "16097",
    "list_language": [],
    "array_tags": [
      "digital",
      "date",
      "battery",
      "steps"
    ],
    "list_album": [
      {
        "id_album": "-1956005621",
        "link_thumb": "https://live.staticflickr.com/65535/51787505874_a5dae981fe_o.gif",
        "title": "None_2"
      }
    ]
  },
  {
    "author": "duelago",
    "link_thumb": "https://live.staticflickr.com/65535/51786884266_3226980a88_o.gif",
    "link_bin": "https://github.com/lmbstudiocontact/mb4_16/raw/main/16098.bin",
    "id_bin": "16098",
    "list_language": [],
    "array_tags": [
      "date",
      "pink",
      "simple",
      "clean",
      "steps"
    ],
    "list_album": [
      {
        "id_album": "-1956005621",
        "link_thumb": "https://live.staticflickr.com/65535/51786884266_3226980a88_o.gif",
        "title": "None_2"
      }
    ]
  },
  {
    "author": "Cubekiss",
    "link_thumb": "https://live.staticflickr.com/65535/51787137328_e4e8d2b5d0_o.gif",
    "link_bin": "https://github.com/lmbstudiocontact/mb4_16/raw/main/16099.bin",
    "id_bin": "16099",
    "list_language": [],
    "array_tags": [
      "digital",
      "date",
      "analog",
      "seconds",
      "battery"
    ],
    "list_album": [
      {
        "id_album": "-1956005621",
        "link_thumb": "https://live.staticflickr.com/65535/51787137328_e4e8d2b5d0_o.gif",
        "title": "None_2"
      }
    ]
  },
  {
    "author": "rsddem",
    "link_thumb": "https://live.staticflickr.com/65535/51786884211_086cef278e_o.gif",
    "link_bin": "https://github.com/lmbstudiocontact/mb4_16/raw/main/16101.bin",
    "id_bin": "16101",
    "list_language": [],
    "array_tags": [
      "battery"
    ],
    "list_album": [
      {
        "id_album": "-1956005621",
        "link_thumb": "https://live.staticflickr.com/65535/51786884211_086cef278e_o.gif",
        "title": "None_2"
      }
    ]
  },
  {
    "author": "boby ahmed",
    "link_thumb": "https://live.staticflickr.com/65535/51786067317_1bb428e039_o.gif",
    "link_bin": "https://github.com/lmbstudiocontact/mb4_16/raw/main/16102.bin",
    "id_bin": "16102",
    "list_language": [],
    "array_tags": [
      "digital",
      "date",
      "battery"
    ],
    "list_album": [
      {
        "id_album": "-1956005621",
        "link_thumb": "https://live.staticflickr.com/65535/51786067317_1bb428e039_o.gif",
        "title": "None_2"
      }
    ]
  },
  {
    "author": "cvg8",
    "link_thumb": "https://live.staticflickr.com/65535/51786884131_3830fcb4e7_o.gif",
    "link_bin": "https://github.com/lmbstudiocontact/mb4_16/raw/main/16104.bin",
    "id_bin": "16104",
    "list_language": [],
    "array_tags": [
      "pink",
      "yellow",
      "rosa"
    ],
    "list_album": [
      {
        "id_album": "-1956005621",
        "link_thumb": "https://live.staticflickr.com/65535/51786884131_3830fcb4e7_o.gif",
        "title": "None_2"
      }
    ]
  },
  {
    "author": "toxicsquall",
    "link_thumb": "https://live.staticflickr.com/65535/51786884116_690c9d38bd_o.gif",
    "link_bin": "https://github.com/lmbstudiocontact/mb4_16/raw/main/16106.bin",
    "id_bin": "16106",
    "list_language": [],
    "array_tags": [
      "digital",
      "date",
      "game",
      "pokemon",
      "heartrate",
      "games",
      "battery"
    ],
    "list_album": [
      {
        "id_album": "-1956005621",
        "link_thumb": "https://live.staticflickr.com/65535/51786884116_690c9d38bd_o.gif",
        "title": "None_2"
      }
    ]
  },
  {
    "author": "HUG_2510",
    "link_thumb": "https://live.staticflickr.com/65535/51787753685_bb5413bdd0_o.gif",
    "link_bin": "https://github.com/lmbstudiocontact/mb4_16/raw/main/16310.bin",
    "id_bin": "16310",
    "list_language": [],
    "array_tags": [
      "digital",
      "distance"
    ],
    "list_album": [
      {
        "id_album": "-1956005621",
        "link_thumb": "https://live.staticflickr.com/65535/51787753685_bb5413bdd0_o.gif",
        "title": "None_2"
      }
    ]
  },
  {
    "author": "AntonioFranklin",
    "link_thumb": "https://live.staticflickr.com/65535/51786880801_7a95e27989_o.gif",
    "link_bin": "https://github.com/lmbstudiocontact/mb4_16/raw/main/16315.bin",
    "id_bin": "16315",
    "list_language": [],
    "array_tags": [
      "digital",
      "date",
      "distance",
      "heartrate",
      "calories",
      "battery",
      "steps"
    ],
    "list_album": [
      {
        "id_album": "-1956005621",
        "link_thumb": "https://live.staticflickr.com/65535/51786880801_7a95e27989_o.gif",
        "title": "None_2"
      }
    ]
  },
  {
    "author": "Ferreirajoel234",
    "link_thumb": "https://live.staticflickr.com/65535/51787753610_3869d76f25_o.gif",
    "link_bin": "https://github.com/lmbstudiocontact/mb4_16/raw/main/16316.bin",
    "id_bin": "16316",
    "list_language": [],
    "array_tags": [
      "digital",
      "analog",
      "seconds"
    ],
    "list_album": [
      {
        "id_album": "-1956005621",
        "link_thumb": "https://live.staticflickr.com/65535/51787753610_3869d76f25_o.gif",
        "title": "None_2"
      }
    ]
  },
  {
    "author": "Luis00",
    "link_thumb": "https://live.staticflickr.com/65535/51787133803_cb018b1897_o.gif",
    "link_bin": "https://github.com/lmbstudiocontact/mb4_16/raw/main/16318.bin",
    "id_bin": "16318",
    "list_language": [],
    "array_tags": [
      "week",
      "data",
      "italiano",
      "days",
      "time"
    ],
    "list_album": [
      {
        "id_album": "-1956005621",
        "link_thumb": "https://live.staticflickr.com/65535/51787133803_cb018b1897_o.gif",
        "title": "None_2"
      }
    ]
  },
  {
    "author": "HAJAH",
    "link_thumb": "https://live.staticflickr.com/65535/51787133778_34e882fa98_o.gif",
    "link_bin": "https://github.com/lmbstudiocontact/mb4_16/raw/main/16319.bin",
    "id_bin": "16319",
    "list_language": [],
    "array_tags": [
      "animado",
      "azul"
    ],
    "list_album": [
      {
        "id_album": "-1956005621",
        "link_thumb": "https://live.staticflickr.com/65535/51787133778_34e882fa98_o.gif",
        "title": "None_2"
      }
    ]
  },
  {
    "author": "andrew72nd",
    "link_thumb": "https://live.staticflickr.com/65535/51787502154_18095a5b93_o.gif",
    "link_bin": "https://github.com/lmbstudiocontact/mb4_16/raw/main/16321.bin",
    "id_bin": "16321",
    "list_language": [],
    "array_tags": [
      "digital",
      "date",
      "distance",
      "heartrate",
      "weekday",
      "battery",
      "steps"
    ],
    "list_album": [
      {
        "id_album": "-1956005621",
        "link_thumb": "https://live.staticflickr.com/65535/51787502154_18095a5b93_o.gif",
        "title": "None_2"
      }
    ]
  },
  {
    "author": "andrew72nd",
    "link_thumb": "https://live.staticflickr.com/65535/51786880666_aea936b0d1_o.gif",
    "link_bin": "https://github.com/lmbstudiocontact/mb4_16/raw/main/16322.bin",
    "id_bin": "16322",
    "list_language": [],
    "array_tags": [
      "mmdd"
    ],
    "list_album": [
      {
        "id_album": "-1956005621",
        "link_thumb": "https://live.staticflickr.com/65535/51786880666_aea936b0d1_o.gif",
        "title": "None_2"
      }
    ]
  },
  {
    "author": "brunih",
    "link_thumb": "https://live.staticflickr.com/65535/51786063362_b830d7fc07_o.gif",
    "link_bin": "https://github.com/lmbstudiocontact/mb4_16/raw/main/16325.bin",
    "id_bin": "16325",
    "list_language": [],
    "array_tags": [
      "digital",
      "distance",
      "battery",
      "steps"
    ],
    "list_album": [
      {
        "id_album": "-1956005621",
        "link_thumb": "https://live.staticflickr.com/65535/51786063362_b830d7fc07_o.gif",
        "title": "None_2"
      }
    ]
  },
  {
    "author": "Artark",
    "link_thumb": "https://live.staticflickr.com/65535/51787502064_ce4fe936cc_o.gif",
    "link_bin": "https://github.com/lmbstudiocontact/mb4_16/raw/main/16326.bin",
    "id_bin": "16326",
    "list_language": [],
    "array_tags": [
      "date",
      "digital",
      "distance",
      "battery"
    ],
    "list_album": [
      {
        "id_album": "-1956005621",
        "link_thumb": "https://live.staticflickr.com/65535/51787502064_ce4fe936cc_o.gif",
        "title": "None_2"
      }
    ]
  },
  {
    "author": "Artark",
    "link_thumb": "https://live.staticflickr.com/65535/51787753445_9c747d0a89_o.gif",
    "link_bin": "https://github.com/lmbstudiocontact/mb4_16/raw/main/16327.bin",
    "id_bin": "16327",
    "list_language": [],
    "array_tags": [
      "date",
      "digital",
      "battery",
      "steps"
    ],
    "list_album": [
      {
        "id_album": "-1956005621",
        "link_thumb": "https://live.staticflickr.com/65535/51787753445_9c747d0a89_o.gif",
        "title": "None_2"
      }
    ]
  },
  {
    "author": "btray05",
    "link_thumb": "https://live.staticflickr.com/65535/51786880591_f57cf7357c_o.gif",
    "link_bin": "https://github.com/lmbstudiocontact/mb4_16/raw/main/16328.bin",
    "id_bin": "16328",
    "list_language": [],
    "array_tags": [
      "date",
      "battery",
      "steps"
    ],
    "list_album": [
      {
        "id_album": "-1956005621",
        "link_thumb": "https://live.staticflickr.com/65535/51786880591_f57cf7357c_o.gif",
        "title": "None_2"
      }
    ]
  },
  {
    "author": "u6gljnuj4l",
    "link_thumb": "https://live.staticflickr.com/65535/51786063192_bc4408c1fc_o.gif",
    "link_bin": "https://github.com/lmbstudiocontact/mb4_16/raw/main/16329.bin",
    "id_bin": "16329",
    "list_language": [],
    "array_tags": [
      "dark",
      "skull",
      "polish"
    ],
    "list_album": [
      {
        "id_album": "-1956005621",
        "link_thumb": "https://live.staticflickr.com/65535/51786063192_bc4408c1fc_o.gif",
        "title": "None_2"
      }
    ]
  },
  {
    "author": "LuisNotDead",
    "link_thumb": "https://live.staticflickr.com/65535/51786880536_89acfe28cb_o.gif",
    "link_bin": "https://github.com/lmbstudiocontact/mb4_16/raw/main/16330.bin",
    "id_bin": "16330",
    "list_language": [],
    "array_tags": [
      "digital",
      "date",
      "distance",
      "heartrate",
      "calories",
      "battery",
      "steps"
    ],
    "list_album": [
      {
        "id_album": "-1956005621",
        "link_thumb": "https://live.staticflickr.com/65535/51786880536_89acfe28cb_o.gif",
        "title": "None_2"
      }
    ]
  }
]